{
  "lastUpdate": "2026-07-18T17:32:36.156Z",
  "lastUpdatePersian": "۱۴۰۵/۴/۲۷, ۱۷:۳۲:۳۶",
  "totalNews": 74,
  "failedSources": [
    "تسنیم",
    "فارس",
    "ایلنا",
    "بی‌بی‌سی فارسی",
    "دویچه‌وله فارسی",
    "رادیو فردا"
  ],
  "categories": [
    "اجتماعی",
    "بین‌الملل",
    "اقتصادی",
    "فرهنگی و هنری",
    "سیاسی",
    "متفرقه",
    "علمی و فناوری",
    "ورزشی"
  ],
  "news": [
    {
      "title": "رادیو اربعین عربی با پوشش ۲۴ ساعته در خوزستان آغاز به کار کرد",
      "link": "https://www.imna.ir/news/989499/%D8%B1%D8%A7%D8%AF%DB%8C%D9%88-%D8%A7%D8%B1%D8%A8%D8%B9%DB%8C%D9%86-%D8%B9%D8%B1%D8%A8%DB%8C-%D8%A8%D8%A7-%D9%BE%D9%88%D8%B4%D8%B4-%DB%B2%DB%B4-%D8%B3%D8%A7%D8%B9%D8%AA%D9%87-%D8%AF%D8%B1-%D8%AE%D9%88%D8%B2%D8%B3%D8%AA%D8%A7%D9%86-%D8%A2%D8%BA%D8%A7%D8%B2-%D8%A8%D9%87-%DA%A9%D8%A7%D8%B1-%DA%A9%D8%B1%D8%AF",
      "date": "Sat, 18 Jul 2026 17:31:27 GMT",
      "source": "ایمنا",
      "category": "اجتماعی",
      "flag": "🇮🇷"
    },
    {
      "title": "صدراعظم آلمان سه چالش اصلی اروپا را نام برد",
      "link": "https://www.isna.ir/news/1405042716173/%D8%B5%D8%AF%D8%B1%D8%A7%D8%B9%D8%B8%D9%85-%D8%A2%D9%84%D9%85%D8%A7%D9%86-%D8%B3%D9%87-%DA%86%D8%A7%D9%84%D8%B4-%D8%A7%D8%B5%D9%84%DB%8C-%D8%A7%D8%B1%D9%88%D9%BE%D8%A7-%D8%B1%D8%A7-%D9%86%D8%A7%D9%85-%D8%A8%D8%B1%D8%AF",
      "date": "Sat, 18 Jul 2026 17:31:07 GMT",
      "source": "ایسنا",
      "category": "بین‌الملل",
      "flag": "🇮🇷"
    },
    {
      "title": "ورود قوه قضاییه به ماجرای اختلال بانکی؛ آیا خسارت مردم جبران می‌شود؟",
      "link": "https://www.khabaronline.ir/news/2248163/%D9%88%D8%B1%D9%88%D8%AF-%D9%82%D9%88%D9%87-%D9%82%D8%B6%D8%A7%DB%8C%DB%8C%D9%87-%D8%A8%D9%87-%D9%85%D8%A7%D8%AC%D8%B1%D8%A7%DB%8C-%D8%A7%D8%AE%D8%AA%D9%84%D8%A7%D9%84-%D8%A8%D8%A7%D9%86%DA%A9%DB%8C-%D8%A2%DB%8C%D8%A7-%D8%AE%D8%B3%D8%A7%D8%B1%D8%AA-%D9%85%D8%B1%D8%AF%D9%85-%D8%AC%D8%A8%D8%B1%D8%A7%D9%86",
      "date": "Sat, 18 Jul 2026 17:30:00 GMT",
      "source": "خبرآنلاین",
      "category": "اقتصادی",
      "flag": "🇮🇷"
    },
    {
      "title": "خط و نشان عضو هیئت رئیسه مجلس درباره حملات آمریکا؛ منافع اقتصادی دونالد ترامپ و داماد وی در منطقه نیز جزء اهداف مشروع جمهوری اسلامی است",
      "link": "https://www.khabaronline.ir/news/2248133/%D8%AE%D8%B7-%D9%88-%D9%86%D8%B4%D8%A7%D9%86-%D8%B9%D8%B6%D9%88-%D9%87%DB%8C%D8%A6%D8%AA-%D8%B1%D8%A6%DB%8C%D8%B3%D9%87-%D9%85%D8%AC%D9%84%D8%B3-%D8%AF%D8%B1%D8%A8%D8%A7%D8%B1%D9%87-%D8%AD%D9%85%D9%84%D8%A7%D8%AA-%D8%A2%D9%85%D8%B1%DB%8C%DA%A9%D8%A7-%D9%85%D9%86%D8%A7%D9%81%D8%B9-%D8%A7%D9%82%D8%AA%D8%B5%D8%A7%D8%AF%DB%8C",
      "date": "Sat, 18 Jul 2026 17:30:00 GMT",
      "source": "خبرآنلاین",
      "category": "بین‌الملل",
      "flag": "🇮🇷"
    },
    {
      "title": "دیدار دوباره بازیگران «قصه‌های مجید» در یک فیلم اجتماعی-جنایی/ «سیاه قلم» به زودی مقابل دوربین می‌رود",
      "link": "https://www.khabaronline.ir/news/2247966/%D8%AF%DB%8C%D8%AF%D8%A7%D8%B1-%D8%AF%D9%88%D8%A8%D8%A7%D8%B1%D9%87-%D8%A8%D8%A7%D8%B2%DB%8C%DA%AF%D8%B1%D8%A7%D9%86-%D9%82%D8%B5%D9%87-%D9%87%D8%A7%DB%8C-%D9%85%D8%AC%DB%8C%D8%AF-%D8%AF%D8%B1-%DB%8C%DA%A9-%D9%81%DB%8C%D9%84%D9%85-%D8%A7%D8%AC%D8%AA%D9%85%D8%A7%D8%B9%DB%8C-%D8%AC%D9%86%D8%A7%DB%8C%DB%8C",
      "date": "Sat, 18 Jul 2026 17:30:00 GMT",
      "source": "خبرآنلاین",
      "category": "فرهنگی و هنری",
      "flag": "🇮🇷"
    },
    {
      "title": "سنتکام از مرگ ۲ سرباز آمریکایی در اردن خبر داد",
      "link": "https://www.isna.ir/news/1405042716172/%D8%B3%D9%86%D8%AA%DA%A9%D8%A7%D9%85-%D8%A7%D8%B2-%D9%85%D8%B1%DA%AF-%DB%B2-%D8%B3%D8%B1%D8%A8%D8%A7%D8%B2-%D8%A2%D9%85%D8%B1%DB%8C%DA%A9%D8%A7%DB%8C%DB%8C-%D8%AF%D8%B1-%D8%A7%D8%B1%D8%AF%D9%86-%D8%AE%D8%A8%D8%B1-%D8%AF%D8%A7%D8%AF",
      "date": "Sat, 18 Jul 2026 17:29:29 GMT",
      "source": "ایسنا",
      "category": "بین‌الملل",
      "flag": "🇮🇷"
    },
    {
      "title": "معاون اول رئیس‌جمهور: با گران‌فروشی و احتکار باید برخورد جدی شود",
      "link": "https://www.imna.ir/news/989500/%D9%85%D8%B9%D8%A7%D9%88%D9%86-%D8%A7%D9%88%D9%84-%D8%B1%D8%A6%DB%8C%D8%B3-%D8%AC%D9%85%D9%87%D9%88%D8%B1-%D8%A8%D8%A7-%DA%AF%D8%B1%D8%A7%D9%86-%D9%81%D8%B1%D9%88%D8%B4%DB%8C-%D9%88-%D8%A7%D8%AD%D8%AA%DA%A9%D8%A7%D8%B1-%D8%A8%D8%A7%DB%8C%D8%AF-%D8%A8%D8%B1%D8%AE%D9%88%D8%B1%D8%AF-%D8%AC%D8%AF%DB%8C",
      "date": "Sat, 18 Jul 2026 17:29:26 GMT",
      "source": "ایمنا",
      "category": "سیاسی",
      "flag": "🇮🇷"
    },
    {
      "title": "محورهای کلیدی پیام رهبر انقلاب؛ بی‌اعتمادی به آمریکا، انسجام و اعتماد عمومی",
      "link": "https://www.imna.ir/news/989480/%D9%85%D8%AD%D9%88%D8%B1%D9%87%D8%A7%DB%8C-%DA%A9%D9%84%DB%8C%D8%AF%DB%8C-%D9%BE%DB%8C%D8%A7%D9%85-%D8%B1%D9%87%D8%A8%D8%B1-%D8%A7%D9%86%D9%82%D9%84%D8%A7%D8%A8-%D8%A8%DB%8C-%D8%A7%D8%B9%D8%AA%D9%85%D8%A7%D8%AF%DB%8C-%D8%A8%D9%87-%D8%A2%D9%85%D8%B1%DB%8C%DA%A9%D8%A7-%D8%A7%D9%86%D8%B3%D8%AC%D8%A7%D9%85",
      "date": "Sat, 18 Jul 2026 17:29:09 GMT",
      "source": "ایمنا",
      "category": "بین‌الملل",
      "flag": "🇮🇷"
    },
    {
      "title": "وقوع یک حادثه دریایی در مقابل سواحل عمان",
      "link": "https://www.isna.ir/news/1405042716171/%D9%88%D9%82%D9%88%D8%B9-%DB%8C%DA%A9-%D8%AD%D8%A7%D8%AF%D8%AB%D9%87-%D8%AF%D8%B1%DB%8C%D8%A7%DB%8C%DB%8C-%D8%AF%D8%B1-%D9%85%D9%82%D8%A7%D8%A8%D9%84-%D8%B3%D9%88%D8%A7%D8%AD%D9%84-%D8%B9%D9%85%D8%A7%D9%86",
      "date": "Sat, 18 Jul 2026 17:28:12 GMT",
      "source": "ایسنا",
      "category": "متفرقه",
      "flag": "🇮🇷"
    },
    {
      "title": "پیگیری صدور مجوزهای زیست محیطی شهرک‌های صنعتی باوی، کارون و حمیدیه",
      "link": "https://www.isna.ir/news/1405042716170/%D9%BE%DB%8C%DA%AF%DB%8C%D8%B1%DB%8C-%D8%B5%D8%AF%D9%88%D8%B1-%D9%85%D8%AC%D9%88%D8%B2%D9%87%D8%A7%DB%8C-%D8%B2%DB%8C%D8%B3%D8%AA-%D9%85%D8%AD%DB%8C%D8%B7%DB%8C-%D8%B4%D9%87%D8%B1%DA%A9-%D9%87%D8%A7%DB%8C-%D8%B5%D9%86%D8%B9%D8%AA%DB%8C-%D8%A8%D8%A7%D9%88%DB%8C-%DA%A9%D8%A7%D8%B1%D9%88%D9%86-%D9%88-%D8%AD%D9%85%DB%8C%D8%AF%DB%8C%D9%87",
      "date": "Sat, 18 Jul 2026 17:27:46 GMT",
      "source": "ایسنا",
      "category": "اقتصادی",
      "flag": "🇮🇷"
    },
    {
      "title": "ادارات هرمزگان یکشنبه ۲۸ تیر با ۵۰ درصد ظرفیت فعالیت می‌کنند",
      "link": "https://www.isna.ir/news/1405042716169/%D9%85%D8%B9%D8%A7%D9%88%D9%86-%D8%A7%D8%B3%D8%AA%D8%A7%D9%86%D8%AF%D8%A7%D8%B1-%D8%A7%D8%AF%D8%A7%D8%B1%D8%A7%D8%AA-%D9%87%D8%B1%D9%85%D8%B2%DA%AF%D8%A7%D9%86-%DB%8C%DA%A9%D8%B4%D9%86%D8%A8%D9%87-%DB%B2%DB%B8-%D8%AA%DB%8C%D8%B1-%D8%A8%D8%A7-%DB%B5%DB%B0-%D8%AF%D8%B1%D8%B5%D8%AF-%D8%B8%D8%B1%D9%81%DB%8C%D8%AA",
      "date": "Sat, 18 Jul 2026 17:27:07 GMT",
      "source": "ایسنا",
      "category": "متفرقه",
      "flag": "🇮🇷"
    },
    {
      "title": "سالانه ۲۱ هزار تن کیوی از عباس‌آباد صادر می‌شود",
      "link": "https://www.mehrnews.com/news/6891869/%D8%B3%D8%A7%D9%84%D8%A7%D9%86%D9%87-%DB%B2%DB%B1-%D9%87%D8%B2%D8%A7%D8%B1-%D8%AA%D9%86-%DA%A9%DB%8C%D9%88%DB%8C-%D8%A7%D8%B2-%D8%B9%D8%A8%D8%A7%D8%B3-%D8%A2%D8%A8%D8%A7%D8%AF-%D8%B5%D8%A7%D8%AF%D8%B1-%D9%85%DB%8C-%D8%B4%D9%88%D8%AF",
      "date": "Sat, 18 Jul 2026 17:26:28 GMT",
      "source": "مهر",
      "category": "متفرقه",
      "flag": "🇮🇷"
    },
    {
      "title": "۲۳ درصد صهیونیست‌ها در اندیشه خروج از اراضی اشغالی در صورت انتخاب مجدد نتانیاهو",
      "link": "https://www.isna.ir/news/1405042716168/%DB%B2%DB%B3-%D8%AF%D8%B1%D8%B5%D8%AF-%D8%B5%D9%87%DB%8C%D9%88%D9%86%DB%8C%D8%B3%D8%AA-%D9%87%D8%A7-%D8%AF%D8%B1-%D8%A7%D9%86%D8%AF%DB%8C%D8%B4%D9%87-%D8%AE%D8%B1%D9%88%D8%AC-%D8%A7%D8%B2-%D8%A7%D8%B1%D8%A7%D8%B6%DB%8C-%D8%A7%D8%B4%D8%BA%D8%A7%D9%84%DB%8C-%D8%AF%D8%B1-%D8%B5%D9%88%D8%B1%D8%AA-%D8%A7%D9%86%D8%AA%D8%AE%D8%A7%D8%A8",
      "date": "Sat, 18 Jul 2026 17:26:11 GMT",
      "source": "ایسنا",
      "category": "متفرقه",
      "flag": "🇮🇷"
    },
    {
      "title": "لاهوتی: بندرچمخاله لنگرود ظرف دو ماه آینده به مرحله بهره‌برداری می‌رسد",
      "link": "https://www.mehrnews.com/news/6891868/%D9%84%D8%A7%D9%87%D9%88%D8%AA%DB%8C-%D8%A8%D9%86%D8%AF%D8%B1%DA%86%D9%85%D8%AE%D8%A7%D9%84%D9%87-%D9%84%D9%86%DA%AF%D8%B1%D9%88%D8%AF-%D8%B8%D8%B1%D9%81-%D8%AF%D9%88-%D9%85%D8%A7%D9%87-%D8%A2%DB%8C%D9%86%D8%AF%D9%87-%D8%A8%D9%87-%D9%85%D8%B1%D8%AD%D9%84%D9%87-%D8%A8%D9%87%D8%B1%D9%87-%D8%A8%D8%B1%D8%AF%D8%A7%D8%B1%DB%8C",
      "date": "Sat, 18 Jul 2026 17:25:45 GMT",
      "source": "مهر",
      "category": "متفرقه",
      "flag": "🇮🇷"
    },
    {
      "title": "مشارکت ۴۶۰ هزار نفر در پویش «مشهد مهربان»",
      "link": "https://www.isna.ir/news/1405042716167/%D9%85%D8%B4%D8%A7%D8%B1%DA%A9%D8%AA-%DB%B4%DB%B6%DB%B0-%D9%87%D8%B2%D8%A7%D8%B1%D9%86%D9%81%D8%B1%DB%8C-%D8%AF%D8%B1-%D9%BE%D9%88%DB%8C%D8%B4-%D9%85%D8%B4%D9%87%D8%AF-%D9%85%D9%87%D8%B1%D8%A8%D8%A7%D9%86",
      "date": "Sat, 18 Jul 2026 17:25:31 GMT",
      "source": "ایسنا",
      "category": "متفرقه",
      "flag": "🇮🇷"
    },
    {
      "title": "اخبار سیاسی ایران؛ امروز شنبه ۲۷ تیر ۱۴۰۵",
      "link": "https://www.imna.ir/news/989489/%D8%A7%D8%AE%D8%A8%D8%A7%D8%B1-%D8%B3%DB%8C%D8%A7%D8%B3%DB%8C-%D8%A7%DB%8C%D8%B1%D8%A7%D9%86-%D8%A7%D9%85%D8%B1%D9%88%D8%B2-%D8%B4%D9%86%D8%A8%D9%87-%DB%B2%DB%B7-%D8%AA%DB%8C%D8%B1-%DB%B1%DB%B4%DB%B0%DB%B5",
      "date": "Sat, 18 Jul 2026 17:25:13 GMT",
      "source": "ایمنا",
      "category": "متفرقه",
      "flag": "🇮🇷"
    },
    {
      "title": "دستور ویژه فتاح برای کمک به مناطق آسیب‌دیده و تأمین آب شرب ۲۰ روستای جاسک",
      "link": "https://www.isna.ir/news/1405042716166/%D8%AF%D8%B3%D8%AA%D9%88%D8%B1-%D9%88%DB%8C%DA%98%D9%87-%D9%81%D8%AA%D8%A7%D8%AD-%D8%A8%D8%B1%D8%A7%DB%8C-%DA%A9%D9%85%DA%A9-%D8%A8%D9%87-%D9%85%D9%86%D8%A7%D8%B7%D9%82-%D8%A2%D8%B3%DB%8C%D8%A8-%D8%AF%DB%8C%D8%AF%D9%87-%D9%88-%D8%AA%D8%A3%D9%85%DB%8C%D9%86-%D8%A2%D8%A8-%D8%B4%D8%B1%D8%A8-%DB%B2%DB%B0",
      "date": "Sat, 18 Jul 2026 17:24:54 GMT",
      "source": "ایسنا",
      "category": "متفرقه",
      "flag": "🇮🇷"
    },
    {
      "title": "آیت الله علم الهدی: سرنوشت شوروی به زودی در انتظار آمریکا است",
      "link": "https://www.irna.ir/news/86212628/%D8%A2%DB%8C%D8%AA-%D8%A7%D9%84%D9%84%D9%87-%D8%B9%D9%84%D9%85-%D8%A7%D9%84%D9%87%D8%AF%DB%8C-%D8%B3%D8%B1%D9%86%D9%88%D8%B4%D8%AA-%D8%B4%D9%88%D8%B1%D9%88%DB%8C-%D8%A8%D9%87-%D8%B2%D9%88%D8%AF%DB%8C-%D8%AF%D8%B1-%D8%A7%D9%86%D8%AA%D8%B8%D8%A7%D8%B1-%D8%A2%D9%85%D8%B1%DB%8C%DA%A9%D8%A7-%D8%A7%D8%B3%D8%AA",
      "date": "Sat, 18 Jul 2026 17:24:49 GMT",
      "source": "ایرنا",
      "category": "علمی و فناوری",
      "flag": "🇮🇷"
    },
    {
      "title": "۸۵۰۰ میلیارد ریال طرح عمرانی در نجف آباد اصفهان به بهره برداری رسید",
      "link": "https://www.irna.ir/news/86212689/%DB%B8%DB%B5%DB%B0%DB%B0-%D9%85%DB%8C%D9%84%DB%8C%D8%A7%D8%B1%D8%AF-%D8%B1%DB%8C%D8%A7%D9%84-%D8%B7%D8%B1%D8%AD-%D8%B9%D9%85%D8%B1%D8%A7%D9%86%DB%8C-%D8%AF%D8%B1-%D9%86%D8%AC%D9%81-%D8%A2%D8%A8%D8%A7%D8%AF-%D8%A7%D8%B5%D9%81%D9%87%D8%A7%D9%86-%D8%A8%D9%87-%D8%A8%D9%87%D8%B1%D9%87-%D8%A8%D8%B1%D8%AF%D8%A7%D8%B1%DB%8C",
      "date": "Sat, 18 Jul 2026 17:24:43 GMT",
      "source": "ایرنا",
      "category": "متفرقه",
      "flag": "🇮🇷"
    },
    {
      "title": "سنتکام: ۲ نظامی آمریکایی در حملات ایران کشته شدند",
      "link": "https://www.mehrnews.com/news/6891871/%D8%B3%D9%86%D8%AA%DA%A9%D8%A7%D9%85-%DB%B2-%D9%86%D8%B8%D8%A7%D9%85%DB%8C-%D8%A2%D9%85%D8%B1%DB%8C%DA%A9%D8%A7%DB%8C%DB%8C-%D8%AF%D8%B1-%D8%AD%D9%85%D9%84%D8%A7%D8%AA-%D8%A7%DB%8C%D8%B1%D8%A7%D9%86-%DA%A9%D8%B4%D8%AA%D9%87-%D8%B4%D8%AF%D9%86%D8%AF",
      "date": "Sat, 18 Jul 2026 17:24:43 GMT",
      "source": "مهر",
      "category": "بین‌الملل",
      "flag": "🇮🇷"
    },
    {
      "title": "توسعه پایدار فراهان نیازمند رویکردی یکپارچه است",
      "link": "https://www.imna.ir/news/989496/%D8%AA%D9%88%D8%B3%D8%B9%D9%87-%D9%BE%D8%A7%DB%8C%D8%AF%D8%A7%D8%B1-%D9%81%D8%B1%D8%A7%D9%87%D8%A7%D9%86-%D9%86%DB%8C%D8%A7%D8%B2%D9%85%D9%86%D8%AF-%D8%B1%D9%88%DB%8C%DA%A9%D8%B1%D8%AF%DB%8C-%DB%8C%DA%A9%D9%BE%D8%A7%D8%B1%DA%86%D9%87-%D8%A7%D8%B3%D8%AA",
      "date": "Sat, 18 Jul 2026 17:24:33 GMT",
      "source": "ایمنا",
      "category": "متفرقه",
      "flag": "🇮🇷"
    },
    {
      "title": "مخاطب رمان «نفرین نوبهاران» انسان هوشمندی است",
      "link": "https://www.irna.ir/news/86212688/%D9%85%D8%AE%D8%A7%D8%B7%D8%A8-%D8%B1%D9%85%D8%A7%D9%86-%D9%86%D9%81%D8%B1%DB%8C%D9%86-%D9%86%D9%88%D8%A8%D9%87%D8%A7%D8%B1%D8%A7%D9%86-%D8%A7%D9%86%D8%B3%D8%A7%D9%86-%D9%87%D9%88%D8%B4%D9%85%D9%86%D8%AF%DB%8C-%D8%A7%D8%B3%D8%AA",
      "date": "Sat, 18 Jul 2026 17:24:24 GMT",
      "source": "ایرنا",
      "category": "متفرقه",
      "flag": "🇮🇷"
    },
    {
      "title": "حضور۳۹۲ تیم در سیزدهمین دوره مسابقات بین المللی رباتیک و هوش مصنوعی",
      "link": "https://www.irna.ir/news/86212696/%D8%AD%D8%B6%D9%88%D8%B1%DB%B3%DB%B9%DB%B2-%D8%AA%DB%8C%D9%85-%D8%AF%D8%B1-%D8%B3%DB%8C%D8%B2%D8%AF%D9%87%D9%85%DB%8C%D9%86-%D8%AF%D9%88%D8%B1%D9%87-%D9%85%D8%B3%D8%A7%D8%A8%D9%82%D8%A7%D8%AA-%D8%A8%DB%8C%D9%86-%D8%A7%D9%84%D9%85%D9%84%D9%84%DB%8C-%D8%B1%D8%A8%D8%A7%D8%AA%DB%8C%DA%A9-%D9%88-%D9%87%D9%88%D8%B4",
      "date": "Sat, 18 Jul 2026 17:24:16 GMT",
      "source": "ایرنا",
      "category": "علمی و فناوری",
      "flag": "🇮🇷"
    },
    {
      "title": "آیا هوش مصنوعی جایگزین مناسبی برای پزشک متخصص است؟",
      "link": "https://www.imna.ir/news/989470/%D8%A2%DB%8C%D8%A7-%D9%87%D9%88%D8%B4-%D9%85%D8%B5%D9%86%D9%88%D8%B9%DB%8C-%D8%AC%D8%A7%DB%8C%DA%AF%D8%B2%DB%8C%D9%86-%D9%85%D9%86%D8%A7%D8%B3%D8%A8%DB%8C-%D8%A8%D8%B1%D8%A7%DB%8C-%D9%BE%D8%B2%D8%B4%DA%A9-%D9%85%D8%AA%D8%AE%D8%B5%D8%B5-%D8%A7%D8%B3%D8%AA",
      "date": "Sat, 18 Jul 2026 17:22:00 GMT",
      "source": "ایمنا",
      "category": "اجتماعی",
      "flag": "🇮🇷"
    },
    {
      "title": "استاندار: تردد در تمام محورهای مواصلاتی هرمزگان برقرار است",
      "link": "https://www.irna.ir/news/86212679/%D8%A7%D8%B3%D8%AA%D8%A7%D9%86%D8%AF%D8%A7%D8%B1-%D8%AA%D8%B1%D8%AF%D8%AF-%D8%AF%D8%B1-%D8%AA%D9%85%D8%A7%D9%85-%D9%85%D8%AD%D9%88%D8%B1%D9%87%D8%A7%DB%8C-%D9%85%D9%88%D8%A7%D8%B5%D9%84%D8%A7%D8%AA%DB%8C-%D9%87%D8%B1%D9%85%D8%B2%DA%AF%D8%A7%D9%86-%D8%A8%D8%B1%D9%82%D8%B1%D8%A7%D8%B1-%D8%A7%D8%B3%D8%AA",
      "date": "Sat, 18 Jul 2026 17:21:01 GMT",
      "source": "ایرنا",
      "category": "متفرقه",
      "flag": "🇮🇷"
    },
    {
      "title": "ویدیو/ هشدار کارشناسان درباره مصرف داروهای خانواده جی‌ال‌پی - ۱",
      "link": "https://www.isna.ir/news/1405042716165/%D9%88%DB%8C%D8%AF%DB%8C%D9%88-%D9%87%D8%B4%D8%AF%D8%A7%D8%B1-%DA%A9%D8%A7%D8%B1%D8%B4%D9%86%D8%A7%D8%B3%D8%A7%D9%86-%D8%AF%D8%B1%D8%A8%D8%A7%D8%B1%D9%87-%D9%85%D8%B5%D8%B1%D9%81-%D8%AF%D8%A7%D8%B1%D9%88%D9%87%D8%A7%DB%8C-%D8%AE%D8%A7%D9%86%D9%88%D8%A7%D8%AF%D9%87-%D8%AC%DB%8C-%D8%A7%D9%84-%D9%BE%DB%8C",
      "date": "Sat, 18 Jul 2026 17:20:48 GMT",
      "source": "ایسنا",
      "category": "اجتماعی",
      "flag": "🇮🇷"
    },
    {
      "title": "افتتاح چهارمین مرکز خدمات روزانه توانبخشی اوتیسم استان مرکزی در خمین",
      "link": "https://www.irna.ir/news/86212697/%D8%A7%D9%81%D8%AA%D8%AA%D8%A7%D8%AD-%DA%86%D9%87%D8%A7%D8%B1%D9%85%DB%8C%D9%86-%D9%85%D8%B1%DA%A9%D8%B2-%D8%AE%D8%AF%D9%85%D8%A7%D8%AA-%D8%B1%D9%88%D8%B2%D8%A7%D9%86%D9%87-%D8%AA%D9%88%D8%A7%D9%86%D8%A8%D8%AE%D8%B4%DB%8C-%D8%A7%D9%88%D8%AA%DB%8C%D8%B3%D9%85-%D8%A7%D8%B3%D8%AA%D8%A7%D9%86-%D9%85%D8%B1%DA%A9%D8%B2%DB%8C",
      "date": "Sat, 18 Jul 2026 17:19:44 GMT",
      "source": "ایرنا",
      "category": "متفرقه",
      "flag": "🇮🇷"
    },
    {
      "title": "بیمارستان کتالم چند ساعت بعد از پلمب با تعهد بهره‌بردار بازگشایی شد",
      "link": "https://www.mehrnews.com/news/6891864/%D8%A8%DB%8C%D9%85%D8%A7%D8%B1%D8%B3%D8%AA%D8%A7%D9%86-%DA%A9%D8%AA%D8%A7%D9%84%D9%85-%DA%86%D9%86%D8%AF-%D8%B3%D8%A7%D8%B9%D8%AA-%D8%A8%D8%B9%D8%AF-%D8%A7%D8%B2-%D9%BE%D9%84%D9%85%D8%A8-%D8%A8%D8%A7-%D8%AA%D8%B9%D9%87%D8%AF-%D8%A8%D9%87%D8%B1%D9%87-%D8%A8%D8%B1%D8%AF%D8%A7%D8%B1-%D8%A8%D8%A7%D8%B2%DA%AF%D8%B4%D8%A7%DB%8C%DB%8C",
      "date": "Sat, 18 Jul 2026 17:19:13 GMT",
      "source": "مهر",
      "category": "اجتماعی",
      "flag": "🇮🇷"
    },
    {
      "title": "اجرای پویش «شوق زیارت» برای اعزام مددجویان خوزستانی به پیاده‌روی اربعین",
      "link": "https://www.imna.ir/news/989494/%D8%A7%D8%AC%D8%B1%D8%A7%DB%8C-%D9%BE%D9%88%DB%8C%D8%B4-%D8%B4%D9%88%D9%82-%D8%B2%DB%8C%D8%A7%D8%B1%D8%AA-%D8%A8%D8%B1%D8%A7%DB%8C-%D8%A7%D8%B9%D8%B2%D8%A7%D9%85-%D9%85%D8%AF%D8%AF%D8%AC%D9%88%DB%8C%D8%A7%D9%86-%D8%AE%D9%88%D8%B2%D8%B3%D8%AA%D8%A7%D9%86%DB%8C-%D8%A8%D9%87-%D9%BE%DB%8C%D8%A7%D8%AF%D9%87-%D8%B1%D9%88%DB%8C",
      "date": "Sat, 18 Jul 2026 17:19:10 GMT",
      "source": "ایمنا",
      "category": "متفرقه",
      "flag": "🇮🇷"
    },
    {
      "title": "قهرمانی دیویس کاپ ایران در گروه ۲ آسیا و اقیانوسیه",
      "link": "https://www.isna.ir/news/1405042716164/%D9%82%D9%87%D8%B1%D9%85%D8%A7%D9%86%DB%8C-%D8%AF%DB%8C%D9%88%DB%8C%D8%B3-%DA%A9%D8%A7%D9%BE-%D8%A7%DB%8C%D8%B1%D8%A7%D9%86-%D8%AF%D8%B1-%DA%AF%D8%B1%D9%88%D9%87-%DB%B2-%D8%A2%D8%B3%DB%8C%D8%A7-%D9%88-%D8%A7%D9%82%DB%8C%D8%A7%D9%86%D9%88%D8%B3%DB%8C%D9%87",
      "date": "Sat, 18 Jul 2026 17:17:46 GMT",
      "source": "ایسنا",
      "category": "ورزشی",
      "flag": "🇮🇷"
    },
    {
      "title": "علامه اقبال یکی از مستحکم‌ترین حلقه‌های پیوند ایران و پاکستان است",
      "link": "https://www.imna.ir/news/989495/%D8%B9%D9%84%D8%A7%D9%85%D9%87-%D8%A7%D9%82%D8%A8%D8%A7%D9%84-%DB%8C%DA%A9%DB%8C-%D8%A7%D8%B2-%D9%85%D8%B3%D8%AA%D8%AD%DA%A9%D9%85-%D8%AA%D8%B1%DB%8C%D9%86-%D8%AD%D9%84%D9%82%D9%87-%D9%87%D8%A7%DB%8C-%D9%BE%DB%8C%D9%88%D9%86%D8%AF-%D8%A7%DB%8C%D8%B1%D8%A7%D9%86-%D9%88-%D9%BE%D8%A7%DA%A9%D8%B3%D8%AA%D8%A7%D9%86",
      "date": "Sat, 18 Jul 2026 17:17:33 GMT",
      "source": "ایمنا",
      "category": "بین‌الملل",
      "flag": "🇮🇷"
    },
    {
      "title": "مهاجرانی: حمله به مناطق اطراف بیمارستان بقایی اهواز در تعارض با حقوق بشر است",
      "link": "https://www.isna.ir/news/1405042716163/%D9%85%D9%87%D8%A7%D8%AC%D8%B1%D8%A7%D9%86%DB%8C-%D8%AD%D9%85%D9%84%D9%87-%D8%A8%D9%87-%D9%85%D9%86%D8%A7%D8%B7%D9%82-%D8%A7%D8%B7%D8%B1%D8%A7%D9%81-%D8%A8%DB%8C%D9%85%D8%A7%D8%B1%D8%B3%D8%AA%D8%A7%D9%86-%D8%A8%D9%82%D8%A7%DB%8C%DB%8C-%D8%A7%D9%87%D9%88%D8%A7%D8%B2-%D8%AF%D8%B1-%D8%AA%D8%B9%D8%A7%D8%B1%D8%B6",
      "date": "Sat, 18 Jul 2026 17:16:40 GMT",
      "source": "ایسنا",
      "category": "اجتماعی",
      "flag": "🇮🇷"
    },
    {
      "title": "اسلامی پس از تمدید قرارداد در تمرین استقلال حاضر شد",
      "link": "https://www.irna.ir/news/86212702/%D8%A7%D8%B3%D9%84%D8%A7%D9%85%DB%8C-%D9%BE%D8%B3-%D8%A7%D8%B2-%D8%AA%D9%85%D8%AF%DB%8C%D8%AF-%D9%82%D8%B1%D8%A7%D8%B1%D8%AF%D8%A7%D8%AF-%D8%AF%D8%B1-%D8%AA%D9%85%D8%B1%DB%8C%D9%86-%D8%A7%D8%B3%D8%AA%D9%82%D9%84%D8%A7%D9%84-%D8%AD%D8%A7%D8%B6%D8%B1-%D8%B4%D8%AF",
      "date": "Sat, 18 Jul 2026 17:15:07 GMT",
      "source": "ایرنا",
      "category": "ورزشی",
      "flag": "🇮🇷"
    },
    {
      "title": "عارف: با گران‌فروشی و احتکار باید برخورد جدی شود",
      "link": "https://www.irna.ir/news/86212699/%D8%B9%D8%A7%D8%B1%D9%81-%D8%A8%D8%A7-%DA%AF%D8%B1%D8%A7%D9%86-%D9%81%D8%B1%D9%88%D8%B4%DB%8C-%D9%88-%D8%A7%D8%AD%D8%AA%DA%A9%D8%A7%D8%B1-%D8%A8%D8%A7%DB%8C%D8%AF-%D8%A8%D8%B1%D8%AE%D9%88%D8%B1%D8%AF-%D8%AC%D8%AF%DB%8C-%D8%B4%D9%88%D8%AF",
      "date": "Sat, 18 Jul 2026 17:15:02 GMT",
      "source": "ایرنا",
      "category": "اجتماعی",
      "flag": "🇮🇷"
    },
    {
      "title": "افشای مشخصات شیائومی ۱۸ پرو/ پادشاه جدید با دوربین ۲۰۰ مگاپیکسلی و باتری ۷۰۰۰ میلی‌آمپری در راه است",
      "link": "https://www.khabaronline.ir/news/2248171/%D8%A7%D9%81%D8%B4%D8%A7%DB%8C-%D9%85%D8%B4%D8%AE%D8%B5%D8%A7%D8%AA-%D8%B4%DB%8C%D8%A7%D8%A6%D9%88%D9%85%DB%8C-%DB%B1%DB%B8-%D9%BE%D8%B1%D9%88-%D9%BE%D8%A7%D8%AF%D8%B4%D8%A7%D9%87-%D8%AC%D8%AF%DB%8C%D8%AF-%D8%A8%D8%A7-%D8%AF%D9%88%D8%B1%D8%A8%DB%8C%D9%86-%DB%B2%DB%B0%DB%B0-%D9%85%DA%AF%D8%A7%D9%BE%DB%8C%DA%A9%D8%B3%D9%84%DB%8C",
      "date": "Sat, 18 Jul 2026 17:15:00 GMT",
      "source": "خبرآنلاین",
      "category": "متفرقه",
      "flag": "🇮🇷"
    },
    {
      "title": "پیام مهم رهبر معظم انقلاب اسلامی خطاب به ملت حماسه‌ساز ایران",
      "link": "https://www.imna.ir/news/989490/%D9%BE%DB%8C%D8%A7%D9%85-%D9%85%D9%87%D9%85-%D8%B1%D9%87%D8%A8%D8%B1-%D9%85%D8%B9%D8%B8%D9%85-%D8%A7%D9%86%D9%82%D9%84%D8%A7%D8%A8-%D8%A7%D8%B3%D9%84%D8%A7%D9%85%DB%8C-%D8%AE%D8%B7%D8%A7%D8%A8-%D8%A8%D9%87-%D9%85%D9%84%D8%AA-%D8%AD%D9%85%D8%A7%D8%B3%D9%87-%D8%B3%D8%A7%D8%B2-%D8%A7%DB%8C%D8%B1%D8%A7%D9%86",
      "date": "Sat, 18 Jul 2026 17:14:28 GMT",
      "source": "ایمنا",
      "category": "سیاسی",
      "flag": "🇮🇷"
    },
    {
      "title": "هشدار استانداری هرمزگان درباره ترددهای غیرضروری در جاده‌ها",
      "link": "https://www.isna.ir/news/1405042716162/%D9%87%D8%B4%D8%AF%D8%A7%D8%B1-%D8%A7%D8%B3%D8%AA%D8%A7%D9%86%D8%AF%D8%A7%D8%B1%DB%8C-%D9%87%D8%B1%D9%85%D8%B2%DA%AF%D8%A7%D9%86-%D8%AF%D8%B1%D8%A8%D8%A7%D8%B1%D9%87-%D8%AA%D8%B1%D8%AF%D8%AF%D9%87%D8%A7%DB%8C-%D8%BA%DB%8C%D8%B1%D8%B6%D8%B1%D9%88%D8%B1%DB%8C-%D8%AF%D8%B1-%D9%85%D8%AD%D9%88%D8%B1%D9%87%D8%A7%DB%8C-%D9%85%D9%88%D8%A7%D8%B5%D9%84%D8%A7%D8%AA%DB%8C",
      "date": "Sat, 18 Jul 2026 17:13:45 GMT",
      "source": "ایسنا",
      "category": "اجتماعی",
      "flag": "🇮🇷"
    },
    {
      "title": "اینفوگرافیک؛ عملکرد پایانه مرزی میرجاوه در سه ماهه نخست ۱۴۰۵",
      "link": "https://www.mehrnews.com/photo/6891638/%D8%A7%DB%8C%D9%86%D9%81%D9%88%DA%AF%D8%B1%D8%A7%D9%81%DB%8C%DA%A9-%D8%B9%D9%85%D9%84%DA%A9%D8%B1%D8%AF-%D9%BE%D8%A7%DB%8C%D8%A7%D9%86%D9%87-%D9%85%D8%B1%D8%B2%DB%8C-%D9%85%DB%8C%D8%B1%D8%AC%D8%A7%D9%88%D9%87-%D8%AF%D8%B1-%D8%B3%D9%87-%D9%85%D8%A7%D9%87%D9%87-%D9%86%D8%AE%D8%B3%D8%AA-%DB%B1%DB%B4%DB%B0%DB%B5",
      "date": "Sat, 18 Jul 2026 17:13:00 GMT",
      "source": "مهر",
      "category": "متفرقه",
      "flag": "🇮🇷"
    },
    {
      "title": "طرح «فانوس‌های نورانی» در بیشه خزایی اجرا می‌شود",
      "link": "https://www.imna.ir/news/987781/%D8%B7%D8%B1%D8%AD-%D9%81%D8%A7%D9%86%D9%88%D8%B3-%D9%87%D8%A7%DB%8C-%D9%86%D9%88%D8%B1%D8%A7%D9%86%DB%8C-%D8%AF%D8%B1-%D8%A8%DB%8C%D8%B4%D9%87-%D8%AE%D8%B2%D8%A7%DB%8C%DB%8C-%D8%A7%D8%AC%D8%B1%D8%A7-%D9%85%DB%8C-%D8%B4%D9%88%D8%AF",
      "date": "Sat, 18 Jul 2026 17:13:00 GMT",
      "source": "ایمنا",
      "category": "متفرقه",
      "flag": "🇮🇷"
    },
    {
      "title": "ببینید | نجات یک خانواده از خودروی در حال غرق شدن",
      "link": "https://www.khabaronline.ir/news/2248191/%D8%A8%D8%A8%DB%8C%D9%86%DB%8C%D8%AF-%D9%86%D8%AC%D8%A7%D8%AA-%DB%8C%DA%A9-%D8%AE%D8%A7%D9%86%D9%88%D8%A7%D8%AF%D9%87-%D8%A7%D8%B2-%D8%AE%D9%88%D8%AF%D8%B1%D9%88%DB%8C-%D8%AF%D8%B1-%D8%AD%D8%A7%D9%84-%D8%BA%D8%B1%D9%82-%D8%B4%D8%AF%D9%86",
      "date": "Sat, 18 Jul 2026 17:12:46 GMT",
      "source": "خبرآنلاین",
      "category": "اجتماعی",
      "flag": "🇮🇷"
    },
    {
      "title": "ببینید | پیام مهم رهبر معظم انقلاب اسلامی خطاب به ملت حماسه ساز ایران",
      "link": "https://www.khabaronline.ir/news/2248206/%D8%A8%D8%A8%DB%8C%D9%86%DB%8C%D8%AF-%D9%BE%DB%8C%D8%A7%D9%85-%D9%85%D9%87%D9%85-%D8%B1%D9%87%D8%A8%D8%B1-%D9%85%D8%B9%D8%B8%D9%85-%D8%A7%D9%86%D9%82%D9%84%D8%A7%D8%A8-%D8%A7%D8%B3%D9%84%D8%A7%D9%85%DB%8C-%D8%AE%D8%B7%D8%A7%D8%A8-%D8%A8%D9%87-%D9%85%D9%84%D8%AA-%D8%AD%D9%85%D8%A7%D8%B3%D9%87-%D8%B3%D8%A7%D8%B2",
      "date": "Sat, 18 Jul 2026 17:12:30 GMT",
      "source": "خبرآنلاین",
      "category": "سیاسی",
      "flag": "🇮🇷"
    },
    {
      "title": "شهادت یکی از رهبران حماس در غرب غزه",
      "link": "https://www.isna.ir/news/1405042716161/%D8%B4%D9%87%D8%A7%D8%AF%D8%AA-%DB%8C%DA%A9%DB%8C-%D8%A7%D8%B2-%D8%B1%D9%87%D8%A8%D8%B1%D8%A7%D9%86-%D8%AD%D9%85%D8%A7%D8%B3-%D8%AF%D8%B1-%D8%BA%D8%B1%D8%A8-%D8%BA%D8%B2%D9%87",
      "date": "Sat, 18 Jul 2026 17:11:33 GMT",
      "source": "ایسنا",
      "category": "سیاسی",
      "flag": "🇮🇷"
    },
    {
      "title": "ترکیب تیم ملی شطرنج ایران مشخص شد",
      "link": "https://www.isna.ir/news/1405042716160/%D8%AA%D8%B1%DA%A9%DB%8C%D8%A8-%D8%AA%DB%8C%D9%85-%D9%85%D9%84%DB%8C-%D8%B4%D8%B7%D8%B1%D9%86%D8%AC-%D8%A7%DB%8C%D8%B1%D8%A7%D9%86-%D9%85%D8%B4%D8%AE%D8%B5-%D8%B4%D8%AF",
      "date": "Sat, 18 Jul 2026 17:10:59 GMT",
      "source": "ایسنا",
      "category": "ورزشی",
      "flag": "🇮🇷"
    },
    {
      "title": "مهار آتش‌سوزی گسترده محل دپوی نخاله‌های بابل پس از ۳۶ ساعت",
      "link": "https://www.mehrnews.com/news/6891861/%D9%85%D9%87%D8%A7%D8%B1-%D8%A2%D8%AA%D8%B4-%D8%B3%D9%88%D8%B2%DB%8C-%DA%AF%D8%B3%D8%AA%D8%B1%D8%AF%D9%87-%D9%85%D8%AD%D9%84-%D8%AF%D9%BE%D9%88%DB%8C-%D9%86%D8%AE%D8%A7%D9%84%D9%87-%D9%87%D8%A7%DB%8C-%D8%A8%D8%A7%D8%A8%D9%84-%D9%BE%D8%B3-%D8%A7%D8%B2-%DB%B3%DB%B6-%D8%B3%D8%A7%D8%B9%D8%AA",
      "date": "Sat, 18 Jul 2026 17:10:00 GMT",
      "source": "مهر",
      "category": "اجتماعی",
      "flag": "🇮🇷"
    },
    {
      "title": "عضو کمیسیون امنیت ملی پاسخ وزیر خارجه فرانسه را داد؛ تازه از واقعیت‌های چهار دهه گذشته آگاه شده‌اید...",
      "link": "https://www.khabaronline.ir/news/2248122/%D8%B9%D8%B6%D9%88-%DA%A9%D9%85%DB%8C%D8%B3%DB%8C%D9%88%D9%86-%D8%A7%D9%85%D9%86%DB%8C%D8%AA-%D9%85%D9%84%DB%8C-%D9%BE%D8%A7%D8%B3%D8%AE-%D9%88%D8%B2%DB%8C%D8%B1-%D8%AE%D8%A7%D8%B1%D8%AC%D9%87-%D9%81%D8%B1%D8%A7%D9%86%D8%B3%D9%87-%D8%B1%D8%A7-%D8%AF%D8%A7%D8%AF-%D8%AA%D8%A7%D8%B2%D9%87-%D8%A7%D8%B2",
      "date": "Sat, 18 Jul 2026 17:10:00 GMT",
      "source": "خبرآنلاین",
      "category": "سیاسی",
      "flag": "🇮🇷"
    },
    {
      "title": "وقوع ۲ انفجار بزرگ به دست اشغالگران در کفرتبنیت در جنوب لبنان+فیلم",
      "link": "https://www.mehrnews.com/news/6891829/%D9%88%D9%82%D9%88%D8%B9-%DB%B2-%D8%A7%D9%86%D9%81%D8%AC%D8%A7%D8%B1-%D8%A8%D8%B2%D8%B1%DA%AF-%D8%A8%D9%87-%D8%AF%D8%B3%D8%AA-%D8%A7%D8%B4%D8%BA%D8%A7%D9%84%DA%AF%D8%B1%D8%A7%D9%86-%D8%AF%D8%B1-%DA%A9%D9%81%D8%B1%D8%AA%D8%A8%D9%86%DB%8C%D8%AA-%D8%AF%D8%B1-%D8%AC%D9%86%D9%88%D8%A8-%D9%84%D8%A8%D9%86%D8%A7%D9%86-%D9%81%DB%8C%D9%84%D9%85",
      "date": "Sat, 18 Jul 2026 17:09:42 GMT",
      "source": "مهر",
      "category": "سیاسی",
      "flag": "🇮🇷"
    },
    {
      "title": "صالحی: علامه اقبال یکی از مستحکم‌ترین حلقه‌های پیوند ایران و پاکستان است",
      "link": "https://www.irna.ir/news/86212690/%D8%B5%D8%A7%D9%84%D8%AD%DB%8C-%D8%B9%D9%84%D8%A7%D9%85%D9%87-%D8%A7%D9%82%D8%A8%D8%A7%D9%84-%DB%8C%DA%A9%DB%8C-%D8%A7%D8%B2-%D9%85%D8%B3%D8%AA%D8%AD%DA%A9%D9%85-%D8%AA%D8%B1%DB%8C%D9%86-%D8%AD%D9%84%D9%82%D9%87-%D9%87%D8%A7%DB%8C-%D9%BE%DB%8C%D9%88%D9%86%D8%AF-%D8%A7%DB%8C%D8%B1%D8%A7%D9%86-%D9%88",
      "date": "Sat, 18 Jul 2026 17:08:53 GMT",
      "source": "ایرنا",
      "category": "بین‌الملل",
      "flag": "🇮🇷"
    },
    {
      "title": "اقدامات آمریکا یادآور رفتار گروه‌های تروریستی است",
      "link": "https://www.imna.ir/news/989492/%D8%A7%D9%82%D8%AF%D8%A7%D9%85%D8%A7%D8%AA-%D8%A2%D9%85%D8%B1%DB%8C%DA%A9%D8%A7-%DB%8C%D8%A7%D8%AF%D8%A2%D9%88%D8%B1-%D8%B1%D9%81%D8%AA%D8%A7%D8%B1-%DA%AF%D8%B1%D9%88%D9%87-%D9%87%D8%A7%DB%8C-%D8%AA%D8%B1%D9%88%D8%B1%DB%8C%D8%B3%D8%AA%DB%8C-%D8%A7%D8%B3%D8%AA",
      "date": "Sat, 18 Jul 2026 17:08:37 GMT",
      "source": "ایمنا",
      "category": "سیاسی",
      "flag": "🇮🇷"
    },
    {
      "title": "عارف: قرارگاه فرماندهی واحد نظارت و بازرسی بر بازار تشکیل شد",
      "link": "https://www.isna.ir/news/1405042716159/%D8%B9%D8%A7%D8%B1%D9%81-%D9%82%D8%B1%D8%A7%D8%B1%DA%AF%D8%A7%D9%87-%D9%81%D8%B1%D9%85%D8%A7%D9%86%D8%AF%D9%87%DB%8C-%D9%88%D8%A7%D8%AD%D8%AF-%D9%86%D8%B8%D8%A7%D8%B1%D8%AA-%D9%88-%D8%A8%D8%A7%D8%B2%D8%B1%D8%B3%DB%8C-%D8%A8%D8%B1-%D8%A8%D8%A7%D8%B2%D8%A7%D8%B1-%D8%AA%D8%B4%DA%A9%DB%8C%D9%84-%D8%B4%D8%AF",
      "date": "Sat, 18 Jul 2026 17:08:20 GMT",
      "source": "ایسنا",
      "category": "اقتصادی",
      "flag": "🇮🇷"
    },
    {
      "title": "حضور ۵۰ درصدی کارکنان ادارات هرمزگان در روز یکشنبه ۲۸ تیرماه",
      "link": "https://www.irna.ir/news/86212698/%D8%AD%D8%B6%D9%88%D8%B1-%DB%B5%DB%B0-%D8%AF%D8%B1%D8%B5%D8%AF%DB%8C-%DA%A9%D8%A7%D8%B1%DA%A9%D9%86%D8%A7%D9%86-%D8%A7%D8%AF%D8%A7%D8%B1%D8%A7%D8%AA-%D9%87%D8%B1%D9%85%D8%B2%DA%AF%D8%A7%D9%86-%D8%AF%D8%B1-%D8%B1%D9%88%D8%B2-%DB%8C%DA%A9%D8%B4%D9%86%D8%A8%D9%87-%DB%B2%DB%B8-%D8%AA%DB%8C%D8%B1%D9%85%D8%A7%D9%87",
      "date": "Sat, 18 Jul 2026 17:07:25 GMT",
      "source": "ایرنا",
      "category": "اجتماعی",
      "flag": "🇮🇷"
    },
    {
      "title": "فیلم | آمادگی مرز خسروی برای تردد زائران اربعین",
      "link": "https://www.irna.ir/news/86212620/%D9%81%DB%8C%D9%84%D9%85-%D8%A2%D9%85%D8%A7%D8%AF%DA%AF%DB%8C-%D9%85%D8%B1%D8%B2-%D8%AE%D8%B3%D8%B1%D9%88%DB%8C-%D8%A8%D8%B1%D8%A7%DB%8C-%D8%AA%D8%B1%D8%AF%D8%AF-%D8%B2%D8%A7%D8%A6%D8%B1%D8%A7%D9%86-%D8%A7%D8%B1%D8%A8%D8%B9%DB%8C%D9%86",
      "date": "Sat, 18 Jul 2026 17:05:27 GMT",
      "source": "ایرنا",
      "category": "فرهنگی و هنری",
      "flag": "🇮🇷"
    },
    {
      "title": "۳۱ تیر؛ آخرین مهلت اظهارنامه مالیاتی املاک اجاری در کردستان",
      "link": "https://www.mehrnews.com/news/6891859/%DB%B3%DB%B1-%D8%AA%DB%8C%D8%B1-%D8%A2%D8%AE%D8%B1%DB%8C%D9%86-%D9%85%D9%87%D9%84%D8%AA-%D8%A7%D8%B8%D9%87%D8%A7%D8%B1%D9%86%D8%A7%D9%85%D9%87-%D9%85%D8%A7%D9%84%DB%8C%D8%A7%D8%AA%DB%8C-%D8%A7%D9%85%D9%84%D8%A7%DA%A9-%D8%A7%D8%AC%D8%A7%D8%B1%DB%8C-%D8%AF%D8%B1-%DA%A9%D8%B1%D8%AF%D8%B3%D8%AA%D8%A7%D9%86",
      "date": "Sat, 18 Jul 2026 17:05:15 GMT",
      "source": "مهر",
      "category": "اقتصادی",
      "flag": "🇮🇷"
    },
    {
      "title": "لحظه برخورد شدید و خطرناک خودروی سواری با موتورسیکلت در پل فردوسی اصفهان + فیلم",
      "link": "https://www.imna.ir/news/989485/%D9%84%D8%AD%D8%B8%D9%87-%D8%A8%D8%B1%D8%AE%D9%88%D8%B1%D8%AF-%D8%B4%D8%AF%DB%8C%D8%AF-%D9%88-%D8%AE%D8%B7%D8%B1%D9%86%D8%A7%DA%A9-%D8%AE%D9%88%D8%AF%D8%B1%D9%88%DB%8C-%D8%B3%D9%88%D8%A7%D8%B1%DB%8C-%D8%A8%D8%A7-%D9%85%D9%88%D8%AA%D9%88%D8%B1%D8%B3%DB%8C%DA%A9%D9%84%D8%AA-%D8%AF%D8%B1-%D9%BE%D9%84-%D9%81%D8%B1%D8%AF%D9%88%D8%B3%DB%8C",
      "date": "Sat, 18 Jul 2026 17:05:01 GMT",
      "source": "ایمنا",
      "category": "فرهنگی و هنری",
      "flag": "🇮🇷"
    },
    {
      "title": "۶۰ ثانیه با خراسان‌شمالی؛ از تجهیز نانوایی‌ها به سوخت دوم تا زنگ خطر هاری",
      "link": "https://www.irna.ir/news/86212700/%DB%B6%DB%B0-%D8%AB%D8%A7%D9%86%DB%8C%D9%87-%D8%A8%D8%A7-%D8%AE%D8%B1%D8%A7%D8%B3%D8%A7%D9%86-%D8%B4%D9%85%D8%A7%D9%84%DB%8C-%D8%A7%D8%B2-%D8%AA%D8%AC%D9%87%DB%8C%D8%B2-%D9%86%D8%A7%D9%86%D9%88%D8%A7%DB%8C%DB%8C-%D9%87%D8%A7-%D8%A8%D9%87-%D8%B3%D9%88%D8%AE%D8%AA-%D8%AF%D9%88%D9%85-%D8%AA%D8%A7",
      "date": "Sat, 18 Jul 2026 17:04:01 GMT",
      "source": "ایرنا",
      "category": "علمی و فناوری",
      "flag": "🇮🇷"
    },
    {
      "title": "ساماندهی کافه‌های تهران و ارتقای نظارت‌های بهداشتی اقدام عملیاتی می‌خواهد",
      "link": "https://www.irna.ir/news/86212694/%D8%B3%D8%A7%D9%85%D8%A7%D9%86%D8%AF%D9%87%DB%8C-%DA%A9%D8%A7%D9%81%D9%87-%D9%87%D8%A7%DB%8C-%D8%AA%D9%87%D8%B1%D8%A7%D9%86-%D9%88-%D8%A7%D8%B1%D8%AA%D9%82%D8%A7%DB%8C-%D9%86%D8%B8%D8%A7%D8%B1%D8%AA-%D9%87%D8%A7%DB%8C-%D8%A8%D9%87%D8%AF%D8%A7%D8%B4%D8%AA%DB%8C-%D8%A7%D9%82%D8%AF%D8%A7%D9%85-%D8%B9%D9%85%D9%84%DB%8C%D8%A7%D8%AA%DB%8C",
      "date": "Sat, 18 Jul 2026 17:03:41 GMT",
      "source": "ایرنا",
      "category": "سیاسی",
      "flag": "🇮🇷"
    },
    {
      "title": "جهش البرز در صدور اسناد مالکیت روستایی و کسب رتبه چهارم کشوری",
      "link": "https://www.imna.ir/news/989483/%D8%AC%D9%87%D8%B4-%D8%A7%D9%84%D8%A8%D8%B1%D8%B2-%D8%AF%D8%B1-%D8%B5%D8%AF%D9%88%D8%B1-%D8%A7%D8%B3%D9%86%D8%A7%D8%AF-%D9%85%D8%A7%D9%84%DA%A9%DB%8C%D8%AA-%D8%B1%D9%88%D8%B3%D8%AA%D8%A7%DB%8C%DB%8C-%D9%88-%DA%A9%D8%B3%D8%A8-%D8%B1%D8%AA%D8%A8%D9%87-%DA%86%D9%87%D8%A7%D8%B1%D9%85-%DA%A9%D8%B4%D9%88%D8%B1%DB%8C",
      "date": "Sat, 18 Jul 2026 17:03:27 GMT",
      "source": "ایمنا",
      "category": "بین‌الملل",
      "flag": "🇮🇷"
    },
    {
      "title": "بازدید رئیس ستاد مرکزی اربعین از مرز خسروی در آستانه اربعین",
      "link": "https://www.mehrnews.com/photo/6891845/%D9%85%D8%B1%D8%B2-%D8%AE%D8%B3%D8%B1%D9%88%DB%8C-%D8%A2%D9%85%D8%A7%D8%AF%D9%87-%D9%85%DB%8C%D8%B2%D8%A8%D8%A7%D9%86%DB%8C-%D8%B4%D8%A7%DB%8C%D8%B3%D8%AA%D9%87-%D8%A7%D8%B2-%D8%B2%D8%A7%D8%A6%D8%B1%D8%A7%D9%86-%D8%A7%D8%B1%D8%A8%D8%B9%DB%8C%D9%86",
      "date": "Sat, 18 Jul 2026 17:02:13 GMT",
      "source": "مهر",
      "category": "متفرقه",
      "flag": "🇮🇷"
    },
    {
      "title": "هوای کدام شهر خوزستان به ۵۰ درجه رسید؟",
      "link": "https://www.mehrnews.com/news/6891857/%D9%87%D9%88%D8%A7%DB%8C-%DA%A9%D8%AF%D8%A7%D9%85-%D8%B4%D9%87%D8%B1-%D8%AE%D9%88%D8%B2%D8%B3%D8%AA%D8%A7%D9%86-%D8%A8%D9%87-%DB%B5%DB%B0-%D8%AF%D8%B1%D8%AC%D9%87-%D8%B1%D8%B3%DB%8C%D8%AF",
      "date": "Sat, 18 Jul 2026 17:02:04 GMT",
      "source": "مهر",
      "category": "متفرقه",
      "flag": "🇮🇷"
    },
    {
      "title": "تیم ملی والیبال نوجوانان ایران بدون شکست بر بام آسیا",
      "link": "https://www.imna.ir/news/989488/%D8%AA%DB%8C%D9%85-%D9%85%D9%84%DB%8C-%D9%88%D8%A7%D9%84%DB%8C%D8%A8%D8%A7%D9%84-%D9%86%D9%88%D8%AC%D9%88%D8%A7%D9%86%D8%A7%D9%86-%D8%A7%DB%8C%D8%B1%D8%A7%D9%86-%D8%A8%D8%AF%D9%88%D9%86-%D8%B4%DA%A9%D8%B3%D8%AA-%D8%A8%D8%B1-%D8%A8%D8%A7%D9%85-%D8%A2%D8%B3%DB%8C%D8%A7",
      "date": "Sat, 18 Jul 2026 17:01:33 GMT",
      "source": "ایمنا",
      "category": "ورزشی",
      "flag": "🇮🇷"
    },
    {
      "title": "پیگیری افزایش سهم دولت در اجرای سامانه‌های نوین آبیاری برای خرده‌مالکان",
      "link": "https://www.irna.ir/news/86212677/%D9%BE%DB%8C%DA%AF%DB%8C%D8%B1%DB%8C-%D8%A7%D9%81%D8%B2%D8%A7%DB%8C%D8%B4-%D8%B3%D9%87%D9%85-%D8%AF%D9%88%D9%84%D8%AA-%D8%AF%D8%B1-%D8%A7%D8%AC%D8%B1%D8%A7%DB%8C-%D8%B3%D8%A7%D9%85%D8%A7%D9%86%D9%87-%D9%87%D8%A7%DB%8C-%D9%86%D9%88%DB%8C%D9%86-%D8%A2%D8%A8%DB%8C%D8%A7%D8%B1%DB%8C-%D8%A8%D8%B1%D8%A7%DB%8C-%D8%AE%D8%B1%D8%AF%D9%87-%D9%85%D8%A7%D9%84%DA%A9%D8%A7%D9%86",
      "date": "Sat, 18 Jul 2026 17:00:56 GMT",
      "source": "ایرنا",
      "category": "سیاسی",
      "flag": "🇮🇷"
    },
    {
      "title": "علوم پزشکی اردبیل بر بهداشت دامداری‌ها جهت جلوگیری از انتقال بیماری به انسان تاکید کرد",
      "link": "https://www.irna.ir/news/86212563/%D8%B9%D9%84%D9%88%D9%85-%D9%BE%D8%B2%D8%B4%DA%A9%DB%8C-%D8%A7%D8%B1%D8%AF%D8%A8%DB%8C%D9%84-%D8%A8%D8%B1-%D8%A8%D9%87%D8%AF%D8%A7%D8%B4%D8%AA-%D8%AF%D8%A7%D9%85%D8%AF%D8%A7%D8%B1%DB%8C-%D9%87%D8%A7-%D8%AC%D9%87%D8%AA-%D8%AC%D9%84%D9%88%DA%AF%DB%8C%D8%B1%DB%8C-%D8%A7%D8%B2-%D8%A7%D9%86%D8%AA%D9%82%D8%A7%D9%84",
      "date": "Sat, 18 Jul 2026 17:00:00 GMT",
      "source": "ایرنا",
      "category": "اجتماعی",
      "flag": "🇮🇷"
    },
    {
      "title": "بخشی از مطالبات گندم‌کاران واریز شد",
      "link": "https://www.khabaronline.ir/news/2248172/%D8%A8%D8%AE%D8%B4%DB%8C-%D8%A7%D8%B2-%D9%85%D8%B7%D8%A7%D9%84%D8%A8%D8%A7%D8%AA-%DA%AF%D9%86%D8%AF%D9%85-%DA%A9%D8%A7%D8%B1%D8%A7%D9%86-%D9%88%D8%A7%D8%B1%DB%8C%D8%B2-%D8%B4%D8%AF",
      "date": "Sat, 18 Jul 2026 17:00:00 GMT",
      "source": "خبرآنلاین",
      "category": "اجتماعی",
      "flag": "🇮🇷"
    },
    {
      "title": "نمایشنامه‌هایی از سیدمهدی شجاعی و سیدحسین فدایی‌حسین در سنگلج",
      "link": "https://www.khabaronline.ir/news/2247962/%D9%86%D9%85%D8%A7%DB%8C%D8%B4%D9%86%D8%A7%D9%85%D9%87-%D9%87%D8%A7%DB%8C%DB%8C-%D8%A7%D8%B2-%D8%B3%DB%8C%D8%AF%D9%85%D9%87%D8%AF%DB%8C-%D8%B4%D8%AC%D8%A7%D8%B9%DB%8C-%D9%88-%D8%B3%DB%8C%D8%AF%D8%AD%D8%B3%DB%8C%D9%86-%D9%81%D8%AF%D8%A7%DB%8C%DB%8C-%D8%AD%D8%B3%DB%8C%D9%86-%D8%AF%D8%B1-%D8%B3%D9%86%DA%AF%D9%84%D8%AC",
      "date": "Sat, 18 Jul 2026 17:00:00 GMT",
      "source": "خبرآنلاین",
      "category": "ورزشی",
      "flag": "🇮🇷"
    },
    {
      "title": "چرا حس درونی برخی افراد با دوره بزرگسالی تطابق ندارد؟",
      "link": "https://www.khabaronline.ir/news/2247728/%DA%86%D8%B1%D8%A7-%D8%AD%D8%B3-%D8%AF%D8%B1%D9%88%D9%86%DB%8C-%D8%A8%D8%B1%D8%AE%DB%8C-%D8%A7%D9%81%D8%B1%D8%A7%D8%AF-%D8%A8%D8%A7-%D8%AF%D9%88%D8%B1%D9%87-%D8%A8%D8%B2%D8%B1%DA%AF%D8%B3%D8%A7%D9%84%DB%8C-%D8%AA%D8%B7%D8%A7%D8%A8%D9%82-%D9%86%D8%AF%D8%A7%D8%B1%D8%AF",
      "date": "Sat, 18 Jul 2026 17:00:00 GMT",
      "source": "خبرآنلاین",
      "category": "متفرقه",
      "flag": "🇮🇷"
    },
    {
      "title": "پنج لکه صنعتی تا دو سال آینده به شهرک صنعتی غیردولتی تبدیل می‌شوند",
      "link": "https://www.mehrnews.com/news/6891856/%D9%BE%D9%86%D8%AC-%D9%84%DA%A9%D9%87-%D8%B5%D9%86%D8%B9%D8%AA%DB%8C-%D8%AA%D8%A7-%D8%AF%D9%88-%D8%B3%D8%A7%D9%84-%D8%A2%DB%8C%D9%86%D8%AF%D9%87-%D8%A8%D9%87-%D8%B4%D9%87%D8%B1%DA%A9-%D8%B5%D9%86%D8%B9%D8%AA%DB%8C-%D8%BA%DB%8C%D8%B1%D8%AF%D9%88%D9%84%D8%AA%DB%8C-%D8%AA%D8%A8%D8%AF%DB%8C%D9%84-%D9%85%DB%8C-%D8%B4%D9%88%D9%86%D8%AF",
      "date": "Sat, 18 Jul 2026 16:59:41 GMT",
      "source": "مهر",
      "category": "سیاسی",
      "flag": "🇮🇷"
    },
    {
      "title": "هزینه ماهانه استفاده از پارکینگ‌های عمومی تهران چقدر است؟",
      "link": "https://www.khabaronline.ir/news/2248165/%D9%87%D8%B2%DB%8C%D9%86%D9%87-%D9%85%D8%A7%D9%87%D8%A7%D9%86%D9%87-%D8%A7%D8%B3%D8%AA%D9%81%D8%A7%D8%AF%D9%87-%D8%A7%D8%B2-%D9%BE%D8%A7%D8%B1%DA%A9%DB%8C%D9%86%DA%AF-%D9%87%D8%A7%DB%8C-%D8%B9%D9%85%D9%88%D9%85%DB%8C-%D8%AA%D9%87%D8%B1%D8%A7%D9%86-%DA%86%D9%82%D8%AF%D8%B1-%D8%A7%D8%B3%D8%AA",
      "date": "Sat, 18 Jul 2026 16:58:00 GMT",
      "source": "خبرآنلاین",
      "category": "متفرقه",
      "flag": "🇮🇷"
    },
    {
      "title": "احداث نخستین شهرک شیلات شمال‌غرب در روستای تازه کند شریف آباد اردبیل",
      "link": "https://www.mehrnews.com/news/6891852/%D8%A7%D8%AD%D8%AF%D8%A7%D8%AB-%D9%86%D8%AE%D8%B3%D8%AA%DB%8C%D9%86-%D8%B4%D9%87%D8%B1%DA%A9-%D8%B4%DB%8C%D9%84%D8%A7%D8%AA-%D8%B4%D9%85%D8%A7%D9%84-%D8%BA%D8%B1%D8%A8-%D8%AF%D8%B1-%D8%B1%D9%88%D8%B3%D8%AA%D8%A7%DB%8C-%D8%AA%D8%A7%D8%B2%D9%87-%DA%A9%D9%86%D8%AF-%D8%B4%D8%B1%DB%8C%D9%81-%D8%A2%D8%A8%D8%A7%D8%AF",
      "date": "Sat, 18 Jul 2026 16:57:50 GMT",
      "source": "مهر",
      "category": "متفرقه",
      "flag": "🇮🇷"
    },
    {
      "title": "مهاجرانی: کشور در تأمین کالاهای اساسی با مشکلی مواجه نشد",
      "link": "https://www.mehrnews.com/news/6891855/%D9%85%D9%87%D8%A7%D8%AC%D8%B1%D8%A7%D9%86%DB%8C-%DA%A9%D8%B4%D9%88%D8%B1-%D8%AF%D8%B1-%D8%AA%D8%A3%D9%85%DB%8C%D9%86-%DA%A9%D8%A7%D9%84%D8%A7%D9%87%D8%A7%DB%8C-%D8%A7%D8%B3%D8%A7%D8%B3%DB%8C-%D8%A8%D8%A7-%D9%85%D8%B4%DA%A9%D9%84%DB%8C-%D9%85%D9%88%D8%A7%D8%AC%D9%87-%D9%86%D8%B4%D8%AF",
      "date": "Sat, 18 Jul 2026 16:57:45 GMT",
      "source": "مهر",
      "category": "اقتصادی",
      "flag": "🇮🇷"
    },
    {
      "title": "وقوع حادثه دریایی برای یک کشتی تجاری نزدیک عمان",
      "link": "https://www.mehrnews.com/news/6891854/%D9%88%D9%82%D9%88%D8%B9-%D8%AD%D8%A7%D8%AF%D8%AB%D9%87-%D8%AF%D8%B1%DB%8C%D8%A7%DB%8C%DB%8C-%D8%A8%D8%B1%D8%A7%DB%8C-%DB%8C%DA%A9-%D9%86%D9%81%D8%AA%DA%A9%D8%B4-%D9%86%D8%B2%D8%AF%DB%8C%DA%A9-%D8%B9%D9%85%D8%A7%D9%86",
      "date": "Sat, 18 Jul 2026 16:57:45 GMT",
      "source": "مهر",
      "category": "ورزشی",
      "flag": "🇮🇷"
    },
    {
      "title": "ایرانی‌ها سالانه ۲۵ میلیون مراجعه بیمارستانی دارند",
      "link": "https://www.mehrnews.com/news/6891836/%D8%A7%DB%8C%D8%B1%D8%A7%D9%86%DB%8C-%D9%87%D8%A7-%D8%B3%D8%A7%D9%84%D8%A7%D9%86%D9%87-%DB%B2%DB%B5-%D9%85%DB%8C%D9%84%DB%8C%D9%88%D9%86-%D9%85%D8%B1%D8%A7%D8%AC%D8%B9%D9%87-%D8%A8%DB%8C%D9%85%D8%A7%D8%B1%D8%B3%D8%AA%D8%A7%D9%86%DB%8C-%D8%AF%D8%A7%D8%B1%D9%86%D8%AF",
      "date": "Sat, 18 Jul 2026 16:55:48 GMT",
      "source": "مهر",
      "category": "اجتماعی",
      "flag": "🇮🇷"
    },
    {
      "title": "حمله به مواضع تروریست‌های ضد ایرانی در سلیمانیه",
      "link": "https://www.khabaronline.ir/news/2248182/%D8%AD%D9%85%D9%84%D9%87-%D8%A8%D9%87-%D9%85%D9%88%D8%A7%D8%B6%D8%B9-%D8%AA%D8%B1%D9%88%D8%B1%DB%8C%D8%B3%D8%AA-%D9%87%D8%A7%DB%8C-%D8%B6%D8%AF-%D8%A7%DB%8C%D8%B1%D8%A7%D9%86%DB%8C-%D8%AF%D8%B1-%D8%B3%D9%84%DB%8C%D9%85%D8%A7%D9%86%DB%8C%D9%87",
      "date": "Sat, 18 Jul 2026 16:50:00 GMT",
      "source": "خبرآنلاین",
      "category": "سیاسی",
      "flag": "🇮🇷"
    },
    {
      "title": "علی مطهری: جنگ فراگیر با آمریکا رخ نمی‌دهد",
      "link": "https://www.khabaronline.ir/news/2248061/%D8%B9%D9%84%DB%8C-%D9%85%D8%B7%D9%87%D8%B1%DB%8C-%D8%AC%D9%86%DA%AF-%D9%81%D8%B1%D8%A7%DA%AF%DB%8C%D8%B1-%D8%A8%D8%A7-%D8%A2%D9%85%D8%B1%DB%8C%DA%A9%D8%A7-%D8%B1%D8%AE-%D9%86%D9%85%DB%8C-%D8%AF%D9%87%D8%AF",
      "date": "Sat, 18 Jul 2026 16:50:00 GMT",
      "source": "خبرآنلاین",
      "category": "سیاسی",
      "flag": "🇮🇷"
    },
    {
      "title": "حضور سه ایرانی در تیم رویایی  آسیا",
      "link": "https://www.khabaronline.ir/news/2248201/%D8%AD%D8%B6%D9%88%D8%B1-%D8%B3%D9%87-%D8%A7%DB%8C%D8%B1%D8%A7%D9%86%DB%8C-%D8%AF%D8%B1-%D8%AA%DB%8C%D9%85-%D8%B1%D9%88%DB%8C%D8%A7%DB%8C%DB%8C-%D8%A2%D8%B3%DB%8C%D8%A7",
      "date": "Sat, 18 Jul 2026 16:43:06 GMT",
      "source": "خبرآنلاین",
      "category": "بین‌الملل",
      "flag": "🇮🇷"
    },
    {
      "title": "دستیار جدید سهراب بختیاری زاده رسما معرفی شد",
      "link": "https://www.khabaronline.ir/news/2248202/%D8%AF%D8%B3%D8%AA%DB%8C%D8%A7%D8%B1-%D8%AC%D8%AF%DB%8C%D8%AF-%D8%B3%D9%87%D8%B1%D8%A7%D8%A8-%D8%A8%D8%AE%D8%AA%DB%8C%D8%A7%D8%B1%DB%8C-%D8%B2%D8%A7%D8%AF%D9%87-%D8%B1%D8%B3%D9%85%D8%A7-%D9%85%D8%B9%D8%B1%D9%81%DB%8C-%D8%B4%D8%AF",
      "date": "Sat, 18 Jul 2026 16:41:50 GMT",
      "source": "خبرآنلاین",
      "category": "متفرقه",
      "flag": "🇮🇷"
    }
  ],
  "categorizedNews": {
    "اجتماعی": [
      {
        "title": "رادیو اربعین عربی با پوشش ۲۴ ساعته در خوزستان آغاز به کار کرد",
        "link": "https://www.imna.ir/news/989499/%D8%B1%D8%A7%D8%AF%DB%8C%D9%88-%D8%A7%D8%B1%D8%A8%D8%B9%DB%8C%D9%86-%D8%B9%D8%B1%D8%A8%DB%8C-%D8%A8%D8%A7-%D9%BE%D9%88%D8%B4%D8%B4-%DB%B2%DB%B4-%D8%B3%D8%A7%D8%B9%D8%AA%D9%87-%D8%AF%D8%B1-%D8%AE%D9%88%D8%B2%D8%B3%D8%AA%D8%A7%D9%86-%D8%A2%D8%BA%D8%A7%D8%B2-%D8%A8%D9%87-%DA%A9%D8%A7%D8%B1-%DA%A9%D8%B1%D8%AF",
        "date": "Sat, 18 Jul 2026 17:31:27 GMT",
        "source": "ایمنا",
        "category": "اجتماعی",
        "flag": "🇮🇷"
      },
      {
        "title": "آیا هوش مصنوعی جایگزین مناسبی برای پزشک متخصص است؟",
        "link": "https://www.imna.ir/news/989470/%D8%A2%DB%8C%D8%A7-%D9%87%D9%88%D8%B4-%D9%85%D8%B5%D9%86%D9%88%D8%B9%DB%8C-%D8%AC%D8%A7%DB%8C%DA%AF%D8%B2%DB%8C%D9%86-%D9%85%D9%86%D8%A7%D8%B3%D8%A8%DB%8C-%D8%A8%D8%B1%D8%A7%DB%8C-%D9%BE%D8%B2%D8%B4%DA%A9-%D9%85%D8%AA%D8%AE%D8%B5%D8%B5-%D8%A7%D8%B3%D8%AA",
        "date": "Sat, 18 Jul 2026 17:22:00 GMT",
        "source": "ایمنا",
        "category": "اجتماعی",
        "flag": "🇮🇷"
      },
      {
        "title": "ویدیو/ هشدار کارشناسان درباره مصرف داروهای خانواده جی‌ال‌پی - ۱",
        "link": "https://www.isna.ir/news/1405042716165/%D9%88%DB%8C%D8%AF%DB%8C%D9%88-%D9%87%D8%B4%D8%AF%D8%A7%D8%B1-%DA%A9%D8%A7%D8%B1%D8%B4%D9%86%D8%A7%D8%B3%D8%A7%D9%86-%D8%AF%D8%B1%D8%A8%D8%A7%D8%B1%D9%87-%D9%85%D8%B5%D8%B1%D9%81-%D8%AF%D8%A7%D8%B1%D9%88%D9%87%D8%A7%DB%8C-%D8%AE%D8%A7%D9%86%D9%88%D8%A7%D8%AF%D9%87-%D8%AC%DB%8C-%D8%A7%D9%84-%D9%BE%DB%8C",
        "date": "Sat, 18 Jul 2026 17:20:48 GMT",
        "source": "ایسنا",
        "category": "اجتماعی",
        "flag": "🇮🇷"
      },
      {
        "title": "بیمارستان کتالم چند ساعت بعد از پلمب با تعهد بهره‌بردار بازگشایی شد",
        "link": "https://www.mehrnews.com/news/6891864/%D8%A8%DB%8C%D9%85%D8%A7%D8%B1%D8%B3%D8%AA%D8%A7%D9%86-%DA%A9%D8%AA%D8%A7%D9%84%D9%85-%DA%86%D9%86%D8%AF-%D8%B3%D8%A7%D8%B9%D8%AA-%D8%A8%D8%B9%D8%AF-%D8%A7%D8%B2-%D9%BE%D9%84%D9%85%D8%A8-%D8%A8%D8%A7-%D8%AA%D8%B9%D9%87%D8%AF-%D8%A8%D9%87%D8%B1%D9%87-%D8%A8%D8%B1%D8%AF%D8%A7%D8%B1-%D8%A8%D8%A7%D8%B2%DA%AF%D8%B4%D8%A7%DB%8C%DB%8C",
        "date": "Sat, 18 Jul 2026 17:19:13 GMT",
        "source": "مهر",
        "category": "اجتماعی",
        "flag": "🇮🇷"
      },
      {
        "title": "مهاجرانی: حمله به مناطق اطراف بیمارستان بقایی اهواز در تعارض با حقوق بشر است",
        "link": "https://www.isna.ir/news/1405042716163/%D9%85%D9%87%D8%A7%D8%AC%D8%B1%D8%A7%D9%86%DB%8C-%D8%AD%D9%85%D9%84%D9%87-%D8%A8%D9%87-%D9%85%D9%86%D8%A7%D8%B7%D9%82-%D8%A7%D8%B7%D8%B1%D8%A7%D9%81-%D8%A8%DB%8C%D9%85%D8%A7%D8%B1%D8%B3%D8%AA%D8%A7%D9%86-%D8%A8%D9%82%D8%A7%DB%8C%DB%8C-%D8%A7%D9%87%D9%88%D8%A7%D8%B2-%D8%AF%D8%B1-%D8%AA%D8%B9%D8%A7%D8%B1%D8%B6",
        "date": "Sat, 18 Jul 2026 17:16:40 GMT",
        "source": "ایسنا",
        "category": "اجتماعی",
        "flag": "🇮🇷"
      },
      {
        "title": "عارف: با گران‌فروشی و احتکار باید برخورد جدی شود",
        "link": "https://www.irna.ir/news/86212699/%D8%B9%D8%A7%D8%B1%D9%81-%D8%A8%D8%A7-%DA%AF%D8%B1%D8%A7%D9%86-%D9%81%D8%B1%D9%88%D8%B4%DB%8C-%D9%88-%D8%A7%D8%AD%D8%AA%DA%A9%D8%A7%D8%B1-%D8%A8%D8%A7%DB%8C%D8%AF-%D8%A8%D8%B1%D8%AE%D9%88%D8%B1%D8%AF-%D8%AC%D8%AF%DB%8C-%D8%B4%D9%88%D8%AF",
        "date": "Sat, 18 Jul 2026 17:15:02 GMT",
        "source": "ایرنا",
        "category": "اجتماعی",
        "flag": "🇮🇷"
      },
      {
        "title": "هشدار استانداری هرمزگان درباره ترددهای غیرضروری در جاده‌ها",
        "link": "https://www.isna.ir/news/1405042716162/%D9%87%D8%B4%D8%AF%D8%A7%D8%B1-%D8%A7%D8%B3%D8%AA%D8%A7%D9%86%D8%AF%D8%A7%D8%B1%DB%8C-%D9%87%D8%B1%D9%85%D8%B2%DA%AF%D8%A7%D9%86-%D8%AF%D8%B1%D8%A8%D8%A7%D8%B1%D9%87-%D8%AA%D8%B1%D8%AF%D8%AF%D9%87%D8%A7%DB%8C-%D8%BA%DB%8C%D8%B1%D8%B6%D8%B1%D9%88%D8%B1%DB%8C-%D8%AF%D8%B1-%D9%85%D8%AD%D9%88%D8%B1%D9%87%D8%A7%DB%8C-%D9%85%D9%88%D8%A7%D8%B5%D9%84%D8%A7%D8%AA%DB%8C",
        "date": "Sat, 18 Jul 2026 17:13:45 GMT",
        "source": "ایسنا",
        "category": "اجتماعی",
        "flag": "🇮🇷"
      },
      {
        "title": "ببینید | نجات یک خانواده از خودروی در حال غرق شدن",
        "link": "https://www.khabaronline.ir/news/2248191/%D8%A8%D8%A8%DB%8C%D9%86%DB%8C%D8%AF-%D9%86%D8%AC%D8%A7%D8%AA-%DB%8C%DA%A9-%D8%AE%D8%A7%D9%86%D9%88%D8%A7%D8%AF%D9%87-%D8%A7%D8%B2-%D8%AE%D9%88%D8%AF%D8%B1%D9%88%DB%8C-%D8%AF%D8%B1-%D8%AD%D8%A7%D9%84-%D8%BA%D8%B1%D9%82-%D8%B4%D8%AF%D9%86",
        "date": "Sat, 18 Jul 2026 17:12:46 GMT",
        "source": "خبرآنلاین",
        "category": "اجتماعی",
        "flag": "🇮🇷"
      },
      {
        "title": "مهار آتش‌سوزی گسترده محل دپوی نخاله‌های بابل پس از ۳۶ ساعت",
        "link": "https://www.mehrnews.com/news/6891861/%D9%85%D9%87%D8%A7%D8%B1-%D8%A2%D8%AA%D8%B4-%D8%B3%D9%88%D8%B2%DB%8C-%DA%AF%D8%B3%D8%AA%D8%B1%D8%AF%D9%87-%D9%85%D8%AD%D9%84-%D8%AF%D9%BE%D9%88%DB%8C-%D9%86%D8%AE%D8%A7%D9%84%D9%87-%D9%87%D8%A7%DB%8C-%D8%A8%D8%A7%D8%A8%D9%84-%D9%BE%D8%B3-%D8%A7%D8%B2-%DB%B3%DB%B6-%D8%B3%D8%A7%D8%B9%D8%AA",
        "date": "Sat, 18 Jul 2026 17:10:00 GMT",
        "source": "مهر",
        "category": "اجتماعی",
        "flag": "🇮🇷"
      },
      {
        "title": "حضور ۵۰ درصدی کارکنان ادارات هرمزگان در روز یکشنبه ۲۸ تیرماه",
        "link": "https://www.irna.ir/news/86212698/%D8%AD%D8%B6%D9%88%D8%B1-%DB%B5%DB%B0-%D8%AF%D8%B1%D8%B5%D8%AF%DB%8C-%DA%A9%D8%A7%D8%B1%DA%A9%D9%86%D8%A7%D9%86-%D8%A7%D8%AF%D8%A7%D8%B1%D8%A7%D8%AA-%D9%87%D8%B1%D9%85%D8%B2%DA%AF%D8%A7%D9%86-%D8%AF%D8%B1-%D8%B1%D9%88%D8%B2-%DB%8C%DA%A9%D8%B4%D9%86%D8%A8%D9%87-%DB%B2%DB%B8-%D8%AA%DB%8C%D8%B1%D9%85%D8%A7%D9%87",
        "date": "Sat, 18 Jul 2026 17:07:25 GMT",
        "source": "ایرنا",
        "category": "اجتماعی",
        "flag": "🇮🇷"
      },
      {
        "title": "علوم پزشکی اردبیل بر بهداشت دامداری‌ها جهت جلوگیری از انتقال بیماری به انسان تاکید کرد",
        "link": "https://www.irna.ir/news/86212563/%D8%B9%D9%84%D9%88%D9%85-%D9%BE%D8%B2%D8%B4%DA%A9%DB%8C-%D8%A7%D8%B1%D8%AF%D8%A8%DB%8C%D9%84-%D8%A8%D8%B1-%D8%A8%D9%87%D8%AF%D8%A7%D8%B4%D8%AA-%D8%AF%D8%A7%D9%85%D8%AF%D8%A7%D8%B1%DB%8C-%D9%87%D8%A7-%D8%AC%D9%87%D8%AA-%D8%AC%D9%84%D9%88%DA%AF%DB%8C%D8%B1%DB%8C-%D8%A7%D8%B2-%D8%A7%D9%86%D8%AA%D9%82%D8%A7%D9%84",
        "date": "Sat, 18 Jul 2026 17:00:00 GMT",
        "source": "ایرنا",
        "category": "اجتماعی",
        "flag": "🇮🇷"
      },
      {
        "title": "بخشی از مطالبات گندم‌کاران واریز شد",
        "link": "https://www.khabaronline.ir/news/2248172/%D8%A8%D8%AE%D8%B4%DB%8C-%D8%A7%D8%B2-%D9%85%D8%B7%D8%A7%D9%84%D8%A8%D8%A7%D8%AA-%DA%AF%D9%86%D8%AF%D9%85-%DA%A9%D8%A7%D8%B1%D8%A7%D9%86-%D9%88%D8%A7%D8%B1%DB%8C%D8%B2-%D8%B4%D8%AF",
        "date": "Sat, 18 Jul 2026 17:00:00 GMT",
        "source": "خبرآنلاین",
        "category": "اجتماعی",
        "flag": "🇮🇷"
      },
      {
        "title": "ایرانی‌ها سالانه ۲۵ میلیون مراجعه بیمارستانی دارند",
        "link": "https://www.mehrnews.com/news/6891836/%D8%A7%DB%8C%D8%B1%D8%A7%D9%86%DB%8C-%D9%87%D8%A7-%D8%B3%D8%A7%D9%84%D8%A7%D9%86%D9%87-%DB%B2%DB%B5-%D9%85%DB%8C%D9%84%DB%8C%D9%88%D9%86-%D9%85%D8%B1%D8%A7%D8%AC%D8%B9%D9%87-%D8%A8%DB%8C%D9%85%D8%A7%D8%B1%D8%B3%D8%AA%D8%A7%D9%86%DB%8C-%D8%AF%D8%A7%D8%B1%D9%86%D8%AF",
        "date": "Sat, 18 Jul 2026 16:55:48 GMT",
        "source": "مهر",
        "category": "اجتماعی",
        "flag": "🇮🇷"
      }
    ],
    "بین‌الملل": [
      {
        "title": "صدراعظم آلمان سه چالش اصلی اروپا را نام برد",
        "link": "https://www.isna.ir/news/1405042716173/%D8%B5%D8%AF%D8%B1%D8%A7%D8%B9%D8%B8%D9%85-%D8%A2%D9%84%D9%85%D8%A7%D9%86-%D8%B3%D9%87-%DA%86%D8%A7%D9%84%D8%B4-%D8%A7%D8%B5%D9%84%DB%8C-%D8%A7%D8%B1%D9%88%D9%BE%D8%A7-%D8%B1%D8%A7-%D9%86%D8%A7%D9%85-%D8%A8%D8%B1%D8%AF",
        "date": "Sat, 18 Jul 2026 17:31:07 GMT",
        "source": "ایسنا",
        "category": "بین‌الملل",
        "flag": "🇮🇷"
      },
      {
        "title": "خط و نشان عضو هیئت رئیسه مجلس درباره حملات آمریکا؛ منافع اقتصادی دونالد ترامپ و داماد وی در منطقه نیز جزء اهداف مشروع جمهوری اسلامی است",
        "link": "https://www.khabaronline.ir/news/2248133/%D8%AE%D8%B7-%D9%88-%D9%86%D8%B4%D8%A7%D9%86-%D8%B9%D8%B6%D9%88-%D9%87%DB%8C%D8%A6%D8%AA-%D8%B1%D8%A6%DB%8C%D8%B3%D9%87-%D9%85%D8%AC%D9%84%D8%B3-%D8%AF%D8%B1%D8%A8%D8%A7%D8%B1%D9%87-%D8%AD%D9%85%D9%84%D8%A7%D8%AA-%D8%A2%D9%85%D8%B1%DB%8C%DA%A9%D8%A7-%D9%85%D9%86%D8%A7%D9%81%D8%B9-%D8%A7%D9%82%D8%AA%D8%B5%D8%A7%D8%AF%DB%8C",
        "date": "Sat, 18 Jul 2026 17:30:00 GMT",
        "source": "خبرآنلاین",
        "category": "بین‌الملل",
        "flag": "🇮🇷"
      },
      {
        "title": "سنتکام از مرگ ۲ سرباز آمریکایی در اردن خبر داد",
        "link": "https://www.isna.ir/news/1405042716172/%D8%B3%D9%86%D8%AA%DA%A9%D8%A7%D9%85-%D8%A7%D8%B2-%D9%85%D8%B1%DA%AF-%DB%B2-%D8%B3%D8%B1%D8%A8%D8%A7%D8%B2-%D8%A2%D9%85%D8%B1%DB%8C%DA%A9%D8%A7%DB%8C%DB%8C-%D8%AF%D8%B1-%D8%A7%D8%B1%D8%AF%D9%86-%D8%AE%D8%A8%D8%B1-%D8%AF%D8%A7%D8%AF",
        "date": "Sat, 18 Jul 2026 17:29:29 GMT",
        "source": "ایسنا",
        "category": "بین‌الملل",
        "flag": "🇮🇷"
      },
      {
        "title": "محورهای کلیدی پیام رهبر انقلاب؛ بی‌اعتمادی به آمریکا، انسجام و اعتماد عمومی",
        "link": "https://www.imna.ir/news/989480/%D9%85%D8%AD%D9%88%D8%B1%D9%87%D8%A7%DB%8C-%DA%A9%D9%84%DB%8C%D8%AF%DB%8C-%D9%BE%DB%8C%D8%A7%D9%85-%D8%B1%D9%87%D8%A8%D8%B1-%D8%A7%D9%86%D9%82%D9%84%D8%A7%D8%A8-%D8%A8%DB%8C-%D8%A7%D8%B9%D8%AA%D9%85%D8%A7%D8%AF%DB%8C-%D8%A8%D9%87-%D8%A2%D9%85%D8%B1%DB%8C%DA%A9%D8%A7-%D8%A7%D9%86%D8%B3%D8%AC%D8%A7%D9%85",
        "date": "Sat, 18 Jul 2026 17:29:09 GMT",
        "source": "ایمنا",
        "category": "بین‌الملل",
        "flag": "🇮🇷"
      },
      {
        "title": "سنتکام: ۲ نظامی آمریکایی در حملات ایران کشته شدند",
        "link": "https://www.mehrnews.com/news/6891871/%D8%B3%D9%86%D8%AA%DA%A9%D8%A7%D9%85-%DB%B2-%D9%86%D8%B8%D8%A7%D9%85%DB%8C-%D8%A2%D9%85%D8%B1%DB%8C%DA%A9%D8%A7%DB%8C%DB%8C-%D8%AF%D8%B1-%D8%AD%D9%85%D9%84%D8%A7%D8%AA-%D8%A7%DB%8C%D8%B1%D8%A7%D9%86-%DA%A9%D8%B4%D8%AA%D9%87-%D8%B4%D8%AF%D9%86%D8%AF",
        "date": "Sat, 18 Jul 2026 17:24:43 GMT",
        "source": "مهر",
        "category": "بین‌الملل",
        "flag": "🇮🇷"
      },
      {
        "title": "علامه اقبال یکی از مستحکم‌ترین حلقه‌های پیوند ایران و پاکستان است",
        "link": "https://www.imna.ir/news/989495/%D8%B9%D9%84%D8%A7%D9%85%D9%87-%D8%A7%D9%82%D8%A8%D8%A7%D9%84-%DB%8C%DA%A9%DB%8C-%D8%A7%D8%B2-%D9%85%D8%B3%D8%AA%D8%AD%DA%A9%D9%85-%D8%AA%D8%B1%DB%8C%D9%86-%D8%AD%D9%84%D9%82%D9%87-%D9%87%D8%A7%DB%8C-%D9%BE%DB%8C%D9%88%D9%86%D8%AF-%D8%A7%DB%8C%D8%B1%D8%A7%D9%86-%D9%88-%D9%BE%D8%A7%DA%A9%D8%B3%D8%AA%D8%A7%D9%86",
        "date": "Sat, 18 Jul 2026 17:17:33 GMT",
        "source": "ایمنا",
        "category": "بین‌الملل",
        "flag": "🇮🇷"
      },
      {
        "title": "صالحی: علامه اقبال یکی از مستحکم‌ترین حلقه‌های پیوند ایران و پاکستان است",
        "link": "https://www.irna.ir/news/86212690/%D8%B5%D8%A7%D9%84%D8%AD%DB%8C-%D8%B9%D9%84%D8%A7%D9%85%D9%87-%D8%A7%D9%82%D8%A8%D8%A7%D9%84-%DB%8C%DA%A9%DB%8C-%D8%A7%D8%B2-%D9%85%D8%B3%D8%AA%D8%AD%DA%A9%D9%85-%D8%AA%D8%B1%DB%8C%D9%86-%D8%AD%D9%84%D9%82%D9%87-%D9%87%D8%A7%DB%8C-%D9%BE%DB%8C%D9%88%D9%86%D8%AF-%D8%A7%DB%8C%D8%B1%D8%A7%D9%86-%D9%88",
        "date": "Sat, 18 Jul 2026 17:08:53 GMT",
        "source": "ایرنا",
        "category": "بین‌الملل",
        "flag": "🇮🇷"
      },
      {
        "title": "جهش البرز در صدور اسناد مالکیت روستایی و کسب رتبه چهارم کشوری",
        "link": "https://www.imna.ir/news/989483/%D8%AC%D9%87%D8%B4-%D8%A7%D9%84%D8%A8%D8%B1%D8%B2-%D8%AF%D8%B1-%D8%B5%D8%AF%D9%88%D8%B1-%D8%A7%D8%B3%D9%86%D8%A7%D8%AF-%D9%85%D8%A7%D9%84%DA%A9%DB%8C%D8%AA-%D8%B1%D9%88%D8%B3%D8%AA%D8%A7%DB%8C%DB%8C-%D9%88-%DA%A9%D8%B3%D8%A8-%D8%B1%D8%AA%D8%A8%D9%87-%DA%86%D9%87%D8%A7%D8%B1%D9%85-%DA%A9%D8%B4%D9%88%D8%B1%DB%8C",
        "date": "Sat, 18 Jul 2026 17:03:27 GMT",
        "source": "ایمنا",
        "category": "بین‌الملل",
        "flag": "🇮🇷"
      },
      {
        "title": "حضور سه ایرانی در تیم رویایی  آسیا",
        "link": "https://www.khabaronline.ir/news/2248201/%D8%AD%D8%B6%D9%88%D8%B1-%D8%B3%D9%87-%D8%A7%DB%8C%D8%B1%D8%A7%D9%86%DB%8C-%D8%AF%D8%B1-%D8%AA%DB%8C%D9%85-%D8%B1%D9%88%DB%8C%D8%A7%DB%8C%DB%8C-%D8%A2%D8%B3%DB%8C%D8%A7",
        "date": "Sat, 18 Jul 2026 16:43:06 GMT",
        "source": "خبرآنلاین",
        "category": "بین‌الملل",
        "flag": "🇮🇷"
      }
    ],
    "اقتصادی": [
      {
        "title": "ورود قوه قضاییه به ماجرای اختلال بانکی؛ آیا خسارت مردم جبران می‌شود؟",
        "link": "https://www.khabaronline.ir/news/2248163/%D9%88%D8%B1%D9%88%D8%AF-%D9%82%D9%88%D9%87-%D9%82%D8%B6%D8%A7%DB%8C%DB%8C%D9%87-%D8%A8%D9%87-%D9%85%D8%A7%D8%AC%D8%B1%D8%A7%DB%8C-%D8%A7%D8%AE%D8%AA%D9%84%D8%A7%D9%84-%D8%A8%D8%A7%D9%86%DA%A9%DB%8C-%D8%A2%DB%8C%D8%A7-%D8%AE%D8%B3%D8%A7%D8%B1%D8%AA-%D9%85%D8%B1%D8%AF%D9%85-%D8%AC%D8%A8%D8%B1%D8%A7%D9%86",
        "date": "Sat, 18 Jul 2026 17:30:00 GMT",
        "source": "خبرآنلاین",
        "category": "اقتصادی",
        "flag": "🇮🇷"
      },
      {
        "title": "پیگیری صدور مجوزهای زیست محیطی شهرک‌های صنعتی باوی، کارون و حمیدیه",
        "link": "https://www.isna.ir/news/1405042716170/%D9%BE%DB%8C%DA%AF%DB%8C%D8%B1%DB%8C-%D8%B5%D8%AF%D9%88%D8%B1-%D9%85%D8%AC%D9%88%D8%B2%D9%87%D8%A7%DB%8C-%D8%B2%DB%8C%D8%B3%D8%AA-%D9%85%D8%AD%DB%8C%D8%B7%DB%8C-%D8%B4%D9%87%D8%B1%DA%A9-%D9%87%D8%A7%DB%8C-%D8%B5%D9%86%D8%B9%D8%AA%DB%8C-%D8%A8%D8%A7%D9%88%DB%8C-%DA%A9%D8%A7%D8%B1%D9%88%D9%86-%D9%88-%D8%AD%D9%85%DB%8C%D8%AF%DB%8C%D9%87",
        "date": "Sat, 18 Jul 2026 17:27:46 GMT",
        "source": "ایسنا",
        "category": "اقتصادی",
        "flag": "🇮🇷"
      },
      {
        "title": "عارف: قرارگاه فرماندهی واحد نظارت و بازرسی بر بازار تشکیل شد",
        "link": "https://www.isna.ir/news/1405042716159/%D8%B9%D8%A7%D8%B1%D9%81-%D9%82%D8%B1%D8%A7%D8%B1%DA%AF%D8%A7%D9%87-%D9%81%D8%B1%D9%85%D8%A7%D9%86%D8%AF%D9%87%DB%8C-%D9%88%D8%A7%D8%AD%D8%AF-%D9%86%D8%B8%D8%A7%D8%B1%D8%AA-%D9%88-%D8%A8%D8%A7%D8%B2%D8%B1%D8%B3%DB%8C-%D8%A8%D8%B1-%D8%A8%D8%A7%D8%B2%D8%A7%D8%B1-%D8%AA%D8%B4%DA%A9%DB%8C%D9%84-%D8%B4%D8%AF",
        "date": "Sat, 18 Jul 2026 17:08:20 GMT",
        "source": "ایسنا",
        "category": "اقتصادی",
        "flag": "🇮🇷"
      },
      {
        "title": "۳۱ تیر؛ آخرین مهلت اظهارنامه مالیاتی املاک اجاری در کردستان",
        "link": "https://www.mehrnews.com/news/6891859/%DB%B3%DB%B1-%D8%AA%DB%8C%D8%B1-%D8%A2%D8%AE%D8%B1%DB%8C%D9%86-%D9%85%D9%87%D9%84%D8%AA-%D8%A7%D8%B8%D9%87%D8%A7%D8%B1%D9%86%D8%A7%D9%85%D9%87-%D9%85%D8%A7%D9%84%DB%8C%D8%A7%D8%AA%DB%8C-%D8%A7%D9%85%D9%84%D8%A7%DA%A9-%D8%A7%D8%AC%D8%A7%D8%B1%DB%8C-%D8%AF%D8%B1-%DA%A9%D8%B1%D8%AF%D8%B3%D8%AA%D8%A7%D9%86",
        "date": "Sat, 18 Jul 2026 17:05:15 GMT",
        "source": "مهر",
        "category": "اقتصادی",
        "flag": "🇮🇷"
      },
      {
        "title": "مهاجرانی: کشور در تأمین کالاهای اساسی با مشکلی مواجه نشد",
        "link": "https://www.mehrnews.com/news/6891855/%D9%85%D9%87%D8%A7%D8%AC%D8%B1%D8%A7%D9%86%DB%8C-%DA%A9%D8%B4%D9%88%D8%B1-%D8%AF%D8%B1-%D8%AA%D8%A3%D9%85%DB%8C%D9%86-%DA%A9%D8%A7%D9%84%D8%A7%D9%87%D8%A7%DB%8C-%D8%A7%D8%B3%D8%A7%D8%B3%DB%8C-%D8%A8%D8%A7-%D9%85%D8%B4%DA%A9%D9%84%DB%8C-%D9%85%D9%88%D8%A7%D8%AC%D9%87-%D9%86%D8%B4%D8%AF",
        "date": "Sat, 18 Jul 2026 16:57:45 GMT",
        "source": "مهر",
        "category": "اقتصادی",
        "flag": "🇮🇷"
      }
    ],
    "فرهنگی و هنری": [
      {
        "title": "دیدار دوباره بازیگران «قصه‌های مجید» در یک فیلم اجتماعی-جنایی/ «سیاه قلم» به زودی مقابل دوربین می‌رود",
        "link": "https://www.khabaronline.ir/news/2247966/%D8%AF%DB%8C%D8%AF%D8%A7%D8%B1-%D8%AF%D9%88%D8%A8%D8%A7%D8%B1%D9%87-%D8%A8%D8%A7%D8%B2%DB%8C%DA%AF%D8%B1%D8%A7%D9%86-%D9%82%D8%B5%D9%87-%D9%87%D8%A7%DB%8C-%D9%85%D8%AC%DB%8C%D8%AF-%D8%AF%D8%B1-%DB%8C%DA%A9-%D9%81%DB%8C%D9%84%D9%85-%D8%A7%D8%AC%D8%AA%D9%85%D8%A7%D8%B9%DB%8C-%D8%AC%D9%86%D8%A7%DB%8C%DB%8C",
        "date": "Sat, 18 Jul 2026 17:30:00 GMT",
        "source": "خبرآنلاین",
        "category": "فرهنگی و هنری",
        "flag": "🇮🇷"
      },
      {
        "title": "فیلم | آمادگی مرز خسروی برای تردد زائران اربعین",
        "link": "https://www.irna.ir/news/86212620/%D9%81%DB%8C%D9%84%D9%85-%D8%A2%D9%85%D8%A7%D8%AF%DA%AF%DB%8C-%D9%85%D8%B1%D8%B2-%D8%AE%D8%B3%D8%B1%D9%88%DB%8C-%D8%A8%D8%B1%D8%A7%DB%8C-%D8%AA%D8%B1%D8%AF%D8%AF-%D8%B2%D8%A7%D8%A6%D8%B1%D8%A7%D9%86-%D8%A7%D8%B1%D8%A8%D8%B9%DB%8C%D9%86",
        "date": "Sat, 18 Jul 2026 17:05:27 GMT",
        "source": "ایرنا",
        "category": "فرهنگی و هنری",
        "flag": "🇮🇷"
      },
      {
        "title": "لحظه برخورد شدید و خطرناک خودروی سواری با موتورسیکلت در پل فردوسی اصفهان + فیلم",
        "link": "https://www.imna.ir/news/989485/%D9%84%D8%AD%D8%B8%D9%87-%D8%A8%D8%B1%D8%AE%D9%88%D8%B1%D8%AF-%D8%B4%D8%AF%DB%8C%D8%AF-%D9%88-%D8%AE%D8%B7%D8%B1%D9%86%D8%A7%DA%A9-%D8%AE%D9%88%D8%AF%D8%B1%D9%88%DB%8C-%D8%B3%D9%88%D8%A7%D8%B1%DB%8C-%D8%A8%D8%A7-%D9%85%D9%88%D8%AA%D9%88%D8%B1%D8%B3%DB%8C%DA%A9%D9%84%D8%AA-%D8%AF%D8%B1-%D9%BE%D9%84-%D9%81%D8%B1%D8%AF%D9%88%D8%B3%DB%8C",
        "date": "Sat, 18 Jul 2026 17:05:01 GMT",
        "source": "ایمنا",
        "category": "فرهنگی و هنری",
        "flag": "🇮🇷"
      }
    ],
    "سیاسی": [
      {
        "title": "معاون اول رئیس‌جمهور: با گران‌فروشی و احتکار باید برخورد جدی شود",
        "link": "https://www.imna.ir/news/989500/%D9%85%D8%B9%D8%A7%D9%88%D9%86-%D8%A7%D9%88%D9%84-%D8%B1%D8%A6%DB%8C%D8%B3-%D8%AC%D9%85%D9%87%D9%88%D8%B1-%D8%A8%D8%A7-%DA%AF%D8%B1%D8%A7%D9%86-%D9%81%D8%B1%D9%88%D8%B4%DB%8C-%D9%88-%D8%A7%D8%AD%D8%AA%DA%A9%D8%A7%D8%B1-%D8%A8%D8%A7%DB%8C%D8%AF-%D8%A8%D8%B1%D8%AE%D9%88%D8%B1%D8%AF-%D8%AC%D8%AF%DB%8C",
        "date": "Sat, 18 Jul 2026 17:29:26 GMT",
        "source": "ایمنا",
        "category": "سیاسی",
        "flag": "🇮🇷"
      },
      {
        "title": "پیام مهم رهبر معظم انقلاب اسلامی خطاب به ملت حماسه‌ساز ایران",
        "link": "https://www.imna.ir/news/989490/%D9%BE%DB%8C%D8%A7%D9%85-%D9%85%D9%87%D9%85-%D8%B1%D9%87%D8%A8%D8%B1-%D9%85%D8%B9%D8%B8%D9%85-%D8%A7%D9%86%D9%82%D9%84%D8%A7%D8%A8-%D8%A7%D8%B3%D9%84%D8%A7%D9%85%DB%8C-%D8%AE%D8%B7%D8%A7%D8%A8-%D8%A8%D9%87-%D9%85%D9%84%D8%AA-%D8%AD%D9%85%D8%A7%D8%B3%D9%87-%D8%B3%D8%A7%D8%B2-%D8%A7%DB%8C%D8%B1%D8%A7%D9%86",
        "date": "Sat, 18 Jul 2026 17:14:28 GMT",
        "source": "ایمنا",
        "category": "سیاسی",
        "flag": "🇮🇷"
      },
      {
        "title": "ببینید | پیام مهم رهبر معظم انقلاب اسلامی خطاب به ملت حماسه ساز ایران",
        "link": "https://www.khabaronline.ir/news/2248206/%D8%A8%D8%A8%DB%8C%D9%86%DB%8C%D8%AF-%D9%BE%DB%8C%D8%A7%D9%85-%D9%85%D9%87%D9%85-%D8%B1%D9%87%D8%A8%D8%B1-%D9%85%D8%B9%D8%B8%D9%85-%D8%A7%D9%86%D9%82%D9%84%D8%A7%D8%A8-%D8%A7%D8%B3%D9%84%D8%A7%D9%85%DB%8C-%D8%AE%D8%B7%D8%A7%D8%A8-%D8%A8%D9%87-%D9%85%D9%84%D8%AA-%D8%AD%D9%85%D8%A7%D8%B3%D9%87-%D8%B3%D8%A7%D8%B2",
        "date": "Sat, 18 Jul 2026 17:12:30 GMT",
        "source": "خبرآنلاین",
        "category": "سیاسی",
        "flag": "🇮🇷"
      },
      {
        "title": "شهادت یکی از رهبران حماس در غرب غزه",
        "link": "https://www.isna.ir/news/1405042716161/%D8%B4%D9%87%D8%A7%D8%AF%D8%AA-%DB%8C%DA%A9%DB%8C-%D8%A7%D8%B2-%D8%B1%D9%87%D8%A8%D8%B1%D8%A7%D9%86-%D8%AD%D9%85%D8%A7%D8%B3-%D8%AF%D8%B1-%D8%BA%D8%B1%D8%A8-%D8%BA%D8%B2%D9%87",
        "date": "Sat, 18 Jul 2026 17:11:33 GMT",
        "source": "ایسنا",
        "category": "سیاسی",
        "flag": "🇮🇷"
      },
      {
        "title": "عضو کمیسیون امنیت ملی پاسخ وزیر خارجه فرانسه را داد؛ تازه از واقعیت‌های چهار دهه گذشته آگاه شده‌اید...",
        "link": "https://www.khabaronline.ir/news/2248122/%D8%B9%D8%B6%D9%88-%DA%A9%D9%85%DB%8C%D8%B3%DB%8C%D9%88%D9%86-%D8%A7%D9%85%D9%86%DB%8C%D8%AA-%D9%85%D9%84%DB%8C-%D9%BE%D8%A7%D8%B3%D8%AE-%D9%88%D8%B2%DB%8C%D8%B1-%D8%AE%D8%A7%D8%B1%D8%AC%D9%87-%D9%81%D8%B1%D8%A7%D9%86%D8%B3%D9%87-%D8%B1%D8%A7-%D8%AF%D8%A7%D8%AF-%D8%AA%D8%A7%D8%B2%D9%87-%D8%A7%D8%B2",
        "date": "Sat, 18 Jul 2026 17:10:00 GMT",
        "source": "خبرآنلاین",
        "category": "سیاسی",
        "flag": "🇮🇷"
      },
      {
        "title": "وقوع ۲ انفجار بزرگ به دست اشغالگران در کفرتبنیت در جنوب لبنان+فیلم",
        "link": "https://www.mehrnews.com/news/6891829/%D9%88%D9%82%D9%88%D8%B9-%DB%B2-%D8%A7%D9%86%D9%81%D8%AC%D8%A7%D8%B1-%D8%A8%D8%B2%D8%B1%DA%AF-%D8%A8%D9%87-%D8%AF%D8%B3%D8%AA-%D8%A7%D8%B4%D8%BA%D8%A7%D9%84%DA%AF%D8%B1%D8%A7%D9%86-%D8%AF%D8%B1-%DA%A9%D9%81%D8%B1%D8%AA%D8%A8%D9%86%DB%8C%D8%AA-%D8%AF%D8%B1-%D8%AC%D9%86%D9%88%D8%A8-%D9%84%D8%A8%D9%86%D8%A7%D9%86-%D9%81%DB%8C%D9%84%D9%85",
        "date": "Sat, 18 Jul 2026 17:09:42 GMT",
        "source": "مهر",
        "category": "سیاسی",
        "flag": "🇮🇷"
      },
      {
        "title": "اقدامات آمریکا یادآور رفتار گروه‌های تروریستی است",
        "link": "https://www.imna.ir/news/989492/%D8%A7%D9%82%D8%AF%D8%A7%D9%85%D8%A7%D8%AA-%D8%A2%D9%85%D8%B1%DB%8C%DA%A9%D8%A7-%DB%8C%D8%A7%D8%AF%D8%A2%D9%88%D8%B1-%D8%B1%D9%81%D8%AA%D8%A7%D8%B1-%DA%AF%D8%B1%D9%88%D9%87-%D9%87%D8%A7%DB%8C-%D8%AA%D8%B1%D9%88%D8%B1%DB%8C%D8%B3%D8%AA%DB%8C-%D8%A7%D8%B3%D8%AA",
        "date": "Sat, 18 Jul 2026 17:08:37 GMT",
        "source": "ایمنا",
        "category": "سیاسی",
        "flag": "🇮🇷"
      },
      {
        "title": "ساماندهی کافه‌های تهران و ارتقای نظارت‌های بهداشتی اقدام عملیاتی می‌خواهد",
        "link": "https://www.irna.ir/news/86212694/%D8%B3%D8%A7%D9%85%D8%A7%D9%86%D8%AF%D9%87%DB%8C-%DA%A9%D8%A7%D9%81%D9%87-%D9%87%D8%A7%DB%8C-%D8%AA%D9%87%D8%B1%D8%A7%D9%86-%D9%88-%D8%A7%D8%B1%D8%AA%D9%82%D8%A7%DB%8C-%D9%86%D8%B8%D8%A7%D8%B1%D8%AA-%D9%87%D8%A7%DB%8C-%D8%A8%D9%87%D8%AF%D8%A7%D8%B4%D8%AA%DB%8C-%D8%A7%D9%82%D8%AF%D8%A7%D9%85-%D8%B9%D9%85%D9%84%DB%8C%D8%A7%D8%AA%DB%8C",
        "date": "Sat, 18 Jul 2026 17:03:41 GMT",
        "source": "ایرنا",
        "category": "سیاسی",
        "flag": "🇮🇷"
      },
      {
        "title": "پیگیری افزایش سهم دولت در اجرای سامانه‌های نوین آبیاری برای خرده‌مالکان",
        "link": "https://www.irna.ir/news/86212677/%D9%BE%DB%8C%DA%AF%DB%8C%D8%B1%DB%8C-%D8%A7%D9%81%D8%B2%D8%A7%DB%8C%D8%B4-%D8%B3%D9%87%D9%85-%D8%AF%D9%88%D9%84%D8%AA-%D8%AF%D8%B1-%D8%A7%D8%AC%D8%B1%D8%A7%DB%8C-%D8%B3%D8%A7%D9%85%D8%A7%D9%86%D9%87-%D9%87%D8%A7%DB%8C-%D9%86%D9%88%DB%8C%D9%86-%D8%A2%D8%A8%DB%8C%D8%A7%D8%B1%DB%8C-%D8%A8%D8%B1%D8%A7%DB%8C-%D8%AE%D8%B1%D8%AF%D9%87-%D9%85%D8%A7%D9%84%DA%A9%D8%A7%D9%86",
        "date": "Sat, 18 Jul 2026 17:00:56 GMT",
        "source": "ایرنا",
        "category": "سیاسی",
        "flag": "🇮🇷"
      },
      {
        "title": "پنج لکه صنعتی تا دو سال آینده به شهرک صنعتی غیردولتی تبدیل می‌شوند",
        "link": "https://www.mehrnews.com/news/6891856/%D9%BE%D9%86%D8%AC-%D9%84%DA%A9%D9%87-%D8%B5%D9%86%D8%B9%D8%AA%DB%8C-%D8%AA%D8%A7-%D8%AF%D9%88-%D8%B3%D8%A7%D9%84-%D8%A2%DB%8C%D9%86%D8%AF%D9%87-%D8%A8%D9%87-%D8%B4%D9%87%D8%B1%DA%A9-%D8%B5%D9%86%D8%B9%D8%AA%DB%8C-%D8%BA%DB%8C%D8%B1%D8%AF%D9%88%D9%84%D8%AA%DB%8C-%D8%AA%D8%A8%D8%AF%DB%8C%D9%84-%D9%85%DB%8C-%D8%B4%D9%88%D9%86%D8%AF",
        "date": "Sat, 18 Jul 2026 16:59:41 GMT",
        "source": "مهر",
        "category": "سیاسی",
        "flag": "🇮🇷"
      },
      {
        "title": "حمله به مواضع تروریست‌های ضد ایرانی در سلیمانیه",
        "link": "https://www.khabaronline.ir/news/2248182/%D8%AD%D9%85%D9%84%D9%87-%D8%A8%D9%87-%D9%85%D9%88%D8%A7%D8%B6%D8%B9-%D8%AA%D8%B1%D9%88%D8%B1%DB%8C%D8%B3%D8%AA-%D9%87%D8%A7%DB%8C-%D8%B6%D8%AF-%D8%A7%DB%8C%D8%B1%D8%A7%D9%86%DB%8C-%D8%AF%D8%B1-%D8%B3%D9%84%DB%8C%D9%85%D8%A7%D9%86%DB%8C%D9%87",
        "date": "Sat, 18 Jul 2026 16:50:00 GMT",
        "source": "خبرآنلاین",
        "category": "سیاسی",
        "flag": "🇮🇷"
      },
      {
        "title": "علی مطهری: جنگ فراگیر با آمریکا رخ نمی‌دهد",
        "link": "https://www.khabaronline.ir/news/2248061/%D8%B9%D9%84%DB%8C-%D9%85%D8%B7%D9%87%D8%B1%DB%8C-%D8%AC%D9%86%DA%AF-%D9%81%D8%B1%D8%A7%DA%AF%DB%8C%D8%B1-%D8%A8%D8%A7-%D8%A2%D9%85%D8%B1%DB%8C%DA%A9%D8%A7-%D8%B1%D8%AE-%D9%86%D9%85%DB%8C-%D8%AF%D9%87%D8%AF",
        "date": "Sat, 18 Jul 2026 16:50:00 GMT",
        "source": "خبرآنلاین",
        "category": "سیاسی",
        "flag": "🇮🇷"
      }
    ],
    "متفرقه": [
      {
        "title": "وقوع یک حادثه دریایی در مقابل سواحل عمان",
        "link": "https://www.isna.ir/news/1405042716171/%D9%88%D9%82%D9%88%D8%B9-%DB%8C%DA%A9-%D8%AD%D8%A7%D8%AF%D8%AB%D9%87-%D8%AF%D8%B1%DB%8C%D8%A7%DB%8C%DB%8C-%D8%AF%D8%B1-%D9%85%D9%82%D8%A7%D8%A8%D9%84-%D8%B3%D9%88%D8%A7%D8%AD%D9%84-%D8%B9%D9%85%D8%A7%D9%86",
        "date": "Sat, 18 Jul 2026 17:28:12 GMT",
        "source": "ایسنا",
        "category": "متفرقه",
        "flag": "🇮🇷"
      },
      {
        "title": "ادارات هرمزگان یکشنبه ۲۸ تیر با ۵۰ درصد ظرفیت فعالیت می‌کنند",
        "link": "https://www.isna.ir/news/1405042716169/%D9%85%D8%B9%D8%A7%D9%88%D9%86-%D8%A7%D8%B3%D8%AA%D8%A7%D9%86%D8%AF%D8%A7%D8%B1-%D8%A7%D8%AF%D8%A7%D8%B1%D8%A7%D8%AA-%D9%87%D8%B1%D9%85%D8%B2%DA%AF%D8%A7%D9%86-%DB%8C%DA%A9%D8%B4%D9%86%D8%A8%D9%87-%DB%B2%DB%B8-%D8%AA%DB%8C%D8%B1-%D8%A8%D8%A7-%DB%B5%DB%B0-%D8%AF%D8%B1%D8%B5%D8%AF-%D8%B8%D8%B1%D9%81%DB%8C%D8%AA",
        "date": "Sat, 18 Jul 2026 17:27:07 GMT",
        "source": "ایسنا",
        "category": "متفرقه",
        "flag": "🇮🇷"
      },
      {
        "title": "سالانه ۲۱ هزار تن کیوی از عباس‌آباد صادر می‌شود",
        "link": "https://www.mehrnews.com/news/6891869/%D8%B3%D8%A7%D9%84%D8%A7%D9%86%D9%87-%DB%B2%DB%B1-%D9%87%D8%B2%D8%A7%D8%B1-%D8%AA%D9%86-%DA%A9%DB%8C%D9%88%DB%8C-%D8%A7%D8%B2-%D8%B9%D8%A8%D8%A7%D8%B3-%D8%A2%D8%A8%D8%A7%D8%AF-%D8%B5%D8%A7%D8%AF%D8%B1-%D9%85%DB%8C-%D8%B4%D9%88%D8%AF",
        "date": "Sat, 18 Jul 2026 17:26:28 GMT",
        "source": "مهر",
        "category": "متفرقه",
        "flag": "🇮🇷"
      },
      {
        "title": "۲۳ درصد صهیونیست‌ها در اندیشه خروج از اراضی اشغالی در صورت انتخاب مجدد نتانیاهو",
        "link": "https://www.isna.ir/news/1405042716168/%DB%B2%DB%B3-%D8%AF%D8%B1%D8%B5%D8%AF-%D8%B5%D9%87%DB%8C%D9%88%D9%86%DB%8C%D8%B3%D8%AA-%D9%87%D8%A7-%D8%AF%D8%B1-%D8%A7%D9%86%D8%AF%DB%8C%D8%B4%D9%87-%D8%AE%D8%B1%D9%88%D8%AC-%D8%A7%D8%B2-%D8%A7%D8%B1%D8%A7%D8%B6%DB%8C-%D8%A7%D8%B4%D8%BA%D8%A7%D9%84%DB%8C-%D8%AF%D8%B1-%D8%B5%D9%88%D8%B1%D8%AA-%D8%A7%D9%86%D8%AA%D8%AE%D8%A7%D8%A8",
        "date": "Sat, 18 Jul 2026 17:26:11 GMT",
        "source": "ایسنا",
        "category": "متفرقه",
        "flag": "🇮🇷"
      },
      {
        "title": "لاهوتی: بندرچمخاله لنگرود ظرف دو ماه آینده به مرحله بهره‌برداری می‌رسد",
        "link": "https://www.mehrnews.com/news/6891868/%D9%84%D8%A7%D9%87%D9%88%D8%AA%DB%8C-%D8%A8%D9%86%D8%AF%D8%B1%DA%86%D9%85%D8%AE%D8%A7%D9%84%D9%87-%D9%84%D9%86%DA%AF%D8%B1%D9%88%D8%AF-%D8%B8%D8%B1%D9%81-%D8%AF%D9%88-%D9%85%D8%A7%D9%87-%D8%A2%DB%8C%D9%86%D8%AF%D9%87-%D8%A8%D9%87-%D9%85%D8%B1%D8%AD%D9%84%D9%87-%D8%A8%D9%87%D8%B1%D9%87-%D8%A8%D8%B1%D8%AF%D8%A7%D8%B1%DB%8C",
        "date": "Sat, 18 Jul 2026 17:25:45 GMT",
        "source": "مهر",
        "category": "متفرقه",
        "flag": "🇮🇷"
      },
      {
        "title": "مشارکت ۴۶۰ هزار نفر در پویش «مشهد مهربان»",
        "link": "https://www.isna.ir/news/1405042716167/%D9%85%D8%B4%D8%A7%D8%B1%DA%A9%D8%AA-%DB%B4%DB%B6%DB%B0-%D9%87%D8%B2%D8%A7%D8%B1%D9%86%D9%81%D8%B1%DB%8C-%D8%AF%D8%B1-%D9%BE%D9%88%DB%8C%D8%B4-%D9%85%D8%B4%D9%87%D8%AF-%D9%85%D9%87%D8%B1%D8%A8%D8%A7%D9%86",
        "date": "Sat, 18 Jul 2026 17:25:31 GMT",
        "source": "ایسنا",
        "category": "متفرقه",
        "flag": "🇮🇷"
      },
      {
        "title": "اخبار سیاسی ایران؛ امروز شنبه ۲۷ تیر ۱۴۰۵",
        "link": "https://www.imna.ir/news/989489/%D8%A7%D8%AE%D8%A8%D8%A7%D8%B1-%D8%B3%DB%8C%D8%A7%D8%B3%DB%8C-%D8%A7%DB%8C%D8%B1%D8%A7%D9%86-%D8%A7%D9%85%D8%B1%D9%88%D8%B2-%D8%B4%D9%86%D8%A8%D9%87-%DB%B2%DB%B7-%D8%AA%DB%8C%D8%B1-%DB%B1%DB%B4%DB%B0%DB%B5",
        "date": "Sat, 18 Jul 2026 17:25:13 GMT",
        "source": "ایمنا",
        "category": "متفرقه",
        "flag": "🇮🇷"
      },
      {
        "title": "دستور ویژه فتاح برای کمک به مناطق آسیب‌دیده و تأمین آب شرب ۲۰ روستای جاسک",
        "link": "https://www.isna.ir/news/1405042716166/%D8%AF%D8%B3%D8%AA%D9%88%D8%B1-%D9%88%DB%8C%DA%98%D9%87-%D9%81%D8%AA%D8%A7%D8%AD-%D8%A8%D8%B1%D8%A7%DB%8C-%DA%A9%D9%85%DA%A9-%D8%A8%D9%87-%D9%85%D9%86%D8%A7%D8%B7%D9%82-%D8%A2%D8%B3%DB%8C%D8%A8-%D8%AF%DB%8C%D8%AF%D9%87-%D9%88-%D8%AA%D8%A3%D9%85%DB%8C%D9%86-%D8%A2%D8%A8-%D8%B4%D8%B1%D8%A8-%DB%B2%DB%B0",
        "date": "Sat, 18 Jul 2026 17:24:54 GMT",
        "source": "ایسنا",
        "category": "متفرقه",
        "flag": "🇮🇷"
      },
      {
        "title": "۸۵۰۰ میلیارد ریال طرح عمرانی در نجف آباد اصفهان به بهره برداری رسید",
        "link": "https://www.irna.ir/news/86212689/%DB%B8%DB%B5%DB%B0%DB%B0-%D9%85%DB%8C%D9%84%DB%8C%D8%A7%D8%B1%D8%AF-%D8%B1%DB%8C%D8%A7%D9%84-%D8%B7%D8%B1%D8%AD-%D8%B9%D9%85%D8%B1%D8%A7%D9%86%DB%8C-%D8%AF%D8%B1-%D9%86%D8%AC%D9%81-%D8%A2%D8%A8%D8%A7%D8%AF-%D8%A7%D8%B5%D9%81%D9%87%D8%A7%D9%86-%D8%A8%D9%87-%D8%A8%D9%87%D8%B1%D9%87-%D8%A8%D8%B1%D8%AF%D8%A7%D8%B1%DB%8C",
        "date": "Sat, 18 Jul 2026 17:24:43 GMT",
        "source": "ایرنا",
        "category": "متفرقه",
        "flag": "🇮🇷"
      },
      {
        "title": "توسعه پایدار فراهان نیازمند رویکردی یکپارچه است",
        "link": "https://www.imna.ir/news/989496/%D8%AA%D9%88%D8%B3%D8%B9%D9%87-%D9%BE%D8%A7%DB%8C%D8%AF%D8%A7%D8%B1-%D9%81%D8%B1%D8%A7%D9%87%D8%A7%D9%86-%D9%86%DB%8C%D8%A7%D8%B2%D9%85%D9%86%D8%AF-%D8%B1%D9%88%DB%8C%DA%A9%D8%B1%D8%AF%DB%8C-%DB%8C%DA%A9%D9%BE%D8%A7%D8%B1%DA%86%D9%87-%D8%A7%D8%B3%D8%AA",
        "date": "Sat, 18 Jul 2026 17:24:33 GMT",
        "source": "ایمنا",
        "category": "متفرقه",
        "flag": "🇮🇷"
      },
      {
        "title": "مخاطب رمان «نفرین نوبهاران» انسان هوشمندی است",
        "link": "https://www.irna.ir/news/86212688/%D9%85%D8%AE%D8%A7%D8%B7%D8%A8-%D8%B1%D9%85%D8%A7%D9%86-%D9%86%D9%81%D8%B1%DB%8C%D9%86-%D9%86%D9%88%D8%A8%D9%87%D8%A7%D8%B1%D8%A7%D9%86-%D8%A7%D9%86%D8%B3%D8%A7%D9%86-%D9%87%D9%88%D8%B4%D9%85%D9%86%D8%AF%DB%8C-%D8%A7%D8%B3%D8%AA",
        "date": "Sat, 18 Jul 2026 17:24:24 GMT",
        "source": "ایرنا",
        "category": "متفرقه",
        "flag": "🇮🇷"
      },
      {
        "title": "استاندار: تردد در تمام محورهای مواصلاتی هرمزگان برقرار است",
        "link": "https://www.irna.ir/news/86212679/%D8%A7%D8%B3%D8%AA%D8%A7%D9%86%D8%AF%D8%A7%D8%B1-%D8%AA%D8%B1%D8%AF%D8%AF-%D8%AF%D8%B1-%D8%AA%D9%85%D8%A7%D9%85-%D9%85%D8%AD%D9%88%D8%B1%D9%87%D8%A7%DB%8C-%D9%85%D9%88%D8%A7%D8%B5%D9%84%D8%A7%D8%AA%DB%8C-%D9%87%D8%B1%D9%85%D8%B2%DA%AF%D8%A7%D9%86-%D8%A8%D8%B1%D9%82%D8%B1%D8%A7%D8%B1-%D8%A7%D8%B3%D8%AA",
        "date": "Sat, 18 Jul 2026 17:21:01 GMT",
        "source": "ایرنا",
        "category": "متفرقه",
        "flag": "🇮🇷"
      },
      {
        "title": "افتتاح چهارمین مرکز خدمات روزانه توانبخشی اوتیسم استان مرکزی در خمین",
        "link": "https://www.irna.ir/news/86212697/%D8%A7%D9%81%D8%AA%D8%AA%D8%A7%D8%AD-%DA%86%D9%87%D8%A7%D8%B1%D9%85%DB%8C%D9%86-%D9%85%D8%B1%DA%A9%D8%B2-%D8%AE%D8%AF%D9%85%D8%A7%D8%AA-%D8%B1%D9%88%D8%B2%D8%A7%D9%86%D9%87-%D8%AA%D9%88%D8%A7%D9%86%D8%A8%D8%AE%D8%B4%DB%8C-%D8%A7%D9%88%D8%AA%DB%8C%D8%B3%D9%85-%D8%A7%D8%B3%D8%AA%D8%A7%D9%86-%D9%85%D8%B1%DA%A9%D8%B2%DB%8C",
        "date": "Sat, 18 Jul 2026 17:19:44 GMT",
        "source": "ایرنا",
        "category": "متفرقه",
        "flag": "🇮🇷"
      },
      {
        "title": "اجرای پویش «شوق زیارت» برای اعزام مددجویان خوزستانی به پیاده‌روی اربعین",
        "link": "https://www.imna.ir/news/989494/%D8%A7%D8%AC%D8%B1%D8%A7%DB%8C-%D9%BE%D9%88%DB%8C%D8%B4-%D8%B4%D9%88%D9%82-%D8%B2%DB%8C%D8%A7%D8%B1%D8%AA-%D8%A8%D8%B1%D8%A7%DB%8C-%D8%A7%D8%B9%D8%B2%D8%A7%D9%85-%D9%85%D8%AF%D8%AF%D8%AC%D9%88%DB%8C%D8%A7%D9%86-%D8%AE%D9%88%D8%B2%D8%B3%D8%AA%D8%A7%D9%86%DB%8C-%D8%A8%D9%87-%D9%BE%DB%8C%D8%A7%D8%AF%D9%87-%D8%B1%D9%88%DB%8C",
        "date": "Sat, 18 Jul 2026 17:19:10 GMT",
        "source": "ایمنا",
        "category": "متفرقه",
        "flag": "🇮🇷"
      },
      {
        "title": "افشای مشخصات شیائومی ۱۸ پرو/ پادشاه جدید با دوربین ۲۰۰ مگاپیکسلی و باتری ۷۰۰۰ میلی‌آمپری در راه است",
        "link": "https://www.khabaronline.ir/news/2248171/%D8%A7%D9%81%D8%B4%D8%A7%DB%8C-%D9%85%D8%B4%D8%AE%D8%B5%D8%A7%D8%AA-%D8%B4%DB%8C%D8%A7%D8%A6%D9%88%D9%85%DB%8C-%DB%B1%DB%B8-%D9%BE%D8%B1%D9%88-%D9%BE%D8%A7%D8%AF%D8%B4%D8%A7%D9%87-%D8%AC%D8%AF%DB%8C%D8%AF-%D8%A8%D8%A7-%D8%AF%D9%88%D8%B1%D8%A8%DB%8C%D9%86-%DB%B2%DB%B0%DB%B0-%D9%85%DA%AF%D8%A7%D9%BE%DB%8C%DA%A9%D8%B3%D9%84%DB%8C",
        "date": "Sat, 18 Jul 2026 17:15:00 GMT",
        "source": "خبرآنلاین",
        "category": "متفرقه",
        "flag": "🇮🇷"
      },
      {
        "title": "اینفوگرافیک؛ عملکرد پایانه مرزی میرجاوه در سه ماهه نخست ۱۴۰۵",
        "link": "https://www.mehrnews.com/photo/6891638/%D8%A7%DB%8C%D9%86%D9%81%D9%88%DA%AF%D8%B1%D8%A7%D9%81%DB%8C%DA%A9-%D8%B9%D9%85%D9%84%DA%A9%D8%B1%D8%AF-%D9%BE%D8%A7%DB%8C%D8%A7%D9%86%D9%87-%D9%85%D8%B1%D8%B2%DB%8C-%D9%85%DB%8C%D8%B1%D8%AC%D8%A7%D9%88%D9%87-%D8%AF%D8%B1-%D8%B3%D9%87-%D9%85%D8%A7%D9%87%D9%87-%D9%86%D8%AE%D8%B3%D8%AA-%DB%B1%DB%B4%DB%B0%DB%B5",
        "date": "Sat, 18 Jul 2026 17:13:00 GMT",
        "source": "مهر",
        "category": "متفرقه",
        "flag": "🇮🇷"
      },
      {
        "title": "طرح «فانوس‌های نورانی» در بیشه خزایی اجرا می‌شود",
        "link": "https://www.imna.ir/news/987781/%D8%B7%D8%B1%D8%AD-%D9%81%D8%A7%D9%86%D9%88%D8%B3-%D9%87%D8%A7%DB%8C-%D9%86%D9%88%D8%B1%D8%A7%D9%86%DB%8C-%D8%AF%D8%B1-%D8%A8%DB%8C%D8%B4%D9%87-%D8%AE%D8%B2%D8%A7%DB%8C%DB%8C-%D8%A7%D8%AC%D8%B1%D8%A7-%D9%85%DB%8C-%D8%B4%D9%88%D8%AF",
        "date": "Sat, 18 Jul 2026 17:13:00 GMT",
        "source": "ایمنا",
        "category": "متفرقه",
        "flag": "🇮🇷"
      },
      {
        "title": "بازدید رئیس ستاد مرکزی اربعین از مرز خسروی در آستانه اربعین",
        "link": "https://www.mehrnews.com/photo/6891845/%D9%85%D8%B1%D8%B2-%D8%AE%D8%B3%D8%B1%D9%88%DB%8C-%D8%A2%D9%85%D8%A7%D8%AF%D9%87-%D9%85%DB%8C%D8%B2%D8%A8%D8%A7%D9%86%DB%8C-%D8%B4%D8%A7%DB%8C%D8%B3%D8%AA%D9%87-%D8%A7%D8%B2-%D8%B2%D8%A7%D8%A6%D8%B1%D8%A7%D9%86-%D8%A7%D8%B1%D8%A8%D8%B9%DB%8C%D9%86",
        "date": "Sat, 18 Jul 2026 17:02:13 GMT",
        "source": "مهر",
        "category": "متفرقه",
        "flag": "🇮🇷"
      },
      {
        "title": "هوای کدام شهر خوزستان به ۵۰ درجه رسید؟",
        "link": "https://www.mehrnews.com/news/6891857/%D9%87%D9%88%D8%A7%DB%8C-%DA%A9%D8%AF%D8%A7%D9%85-%D8%B4%D9%87%D8%B1-%D8%AE%D9%88%D8%B2%D8%B3%D8%AA%D8%A7%D9%86-%D8%A8%D9%87-%DB%B5%DB%B0-%D8%AF%D8%B1%D8%AC%D9%87-%D8%B1%D8%B3%DB%8C%D8%AF",
        "date": "Sat, 18 Jul 2026 17:02:04 GMT",
        "source": "مهر",
        "category": "متفرقه",
        "flag": "🇮🇷"
      },
      {
        "title": "چرا حس درونی برخی افراد با دوره بزرگسالی تطابق ندارد؟",
        "link": "https://www.khabaronline.ir/news/2247728/%DA%86%D8%B1%D8%A7-%D8%AD%D8%B3-%D8%AF%D8%B1%D9%88%D9%86%DB%8C-%D8%A8%D8%B1%D8%AE%DB%8C-%D8%A7%D9%81%D8%B1%D8%A7%D8%AF-%D8%A8%D8%A7-%D8%AF%D9%88%D8%B1%D9%87-%D8%A8%D8%B2%D8%B1%DA%AF%D8%B3%D8%A7%D9%84%DB%8C-%D8%AA%D8%B7%D8%A7%D8%A8%D9%82-%D9%86%D8%AF%D8%A7%D8%B1%D8%AF",
        "date": "Sat, 18 Jul 2026 17:00:00 GMT",
        "source": "خبرآنلاین",
        "category": "متفرقه",
        "flag": "🇮🇷"
      },
      {
        "title": "هزینه ماهانه استفاده از پارکینگ‌های عمومی تهران چقدر است؟",
        "link": "https://www.khabaronline.ir/news/2248165/%D9%87%D8%B2%DB%8C%D9%86%D9%87-%D9%85%D8%A7%D9%87%D8%A7%D9%86%D9%87-%D8%A7%D8%B3%D8%AA%D9%81%D8%A7%D8%AF%D9%87-%D8%A7%D8%B2-%D9%BE%D8%A7%D8%B1%DA%A9%DB%8C%D9%86%DA%AF-%D9%87%D8%A7%DB%8C-%D8%B9%D9%85%D9%88%D9%85%DB%8C-%D8%AA%D9%87%D8%B1%D8%A7%D9%86-%DA%86%D9%82%D8%AF%D8%B1-%D8%A7%D8%B3%D8%AA",
        "date": "Sat, 18 Jul 2026 16:58:00 GMT",
        "source": "خبرآنلاین",
        "category": "متفرقه",
        "flag": "🇮🇷"
      },
      {
        "title": "احداث نخستین شهرک شیلات شمال‌غرب در روستای تازه کند شریف آباد اردبیل",
        "link": "https://www.mehrnews.com/news/6891852/%D8%A7%D8%AD%D8%AF%D8%A7%D8%AB-%D9%86%D8%AE%D8%B3%D8%AA%DB%8C%D9%86-%D8%B4%D9%87%D8%B1%DA%A9-%D8%B4%DB%8C%D9%84%D8%A7%D8%AA-%D8%B4%D9%85%D8%A7%D9%84-%D8%BA%D8%B1%D8%A8-%D8%AF%D8%B1-%D8%B1%D9%88%D8%B3%D8%AA%D8%A7%DB%8C-%D8%AA%D8%A7%D8%B2%D9%87-%DA%A9%D9%86%D8%AF-%D8%B4%D8%B1%DB%8C%D9%81-%D8%A2%D8%A8%D8%A7%D8%AF",
        "date": "Sat, 18 Jul 2026 16:57:50 GMT",
        "source": "مهر",
        "category": "متفرقه",
        "flag": "🇮🇷"
      },
      {
        "title": "دستیار جدید سهراب بختیاری زاده رسما معرفی شد",
        "link": "https://www.khabaronline.ir/news/2248202/%D8%AF%D8%B3%D8%AA%DB%8C%D8%A7%D8%B1-%D8%AC%D8%AF%DB%8C%D8%AF-%D8%B3%D9%87%D8%B1%D8%A7%D8%A8-%D8%A8%D8%AE%D8%AA%DB%8C%D8%A7%D8%B1%DB%8C-%D8%B2%D8%A7%D8%AF%D9%87-%D8%B1%D8%B3%D9%85%D8%A7-%D9%85%D8%B9%D8%B1%D9%81%DB%8C-%D8%B4%D8%AF",
        "date": "Sat, 18 Jul 2026 16:41:50 GMT",
        "source": "خبرآنلاین",
        "category": "متفرقه",
        "flag": "🇮🇷"
      }
    ],
    "علمی و فناوری": [
      {
        "title": "آیت الله علم الهدی: سرنوشت شوروی به زودی در انتظار آمریکا است",
        "link": "https://www.irna.ir/news/86212628/%D8%A2%DB%8C%D8%AA-%D8%A7%D9%84%D9%84%D9%87-%D8%B9%D9%84%D9%85-%D8%A7%D9%84%D9%87%D8%AF%DB%8C-%D8%B3%D8%B1%D9%86%D9%88%D8%B4%D8%AA-%D8%B4%D9%88%D8%B1%D9%88%DB%8C-%D8%A8%D9%87-%D8%B2%D9%88%D8%AF%DB%8C-%D8%AF%D8%B1-%D8%A7%D9%86%D8%AA%D8%B8%D8%A7%D8%B1-%D8%A2%D9%85%D8%B1%DB%8C%DA%A9%D8%A7-%D8%A7%D8%B3%D8%AA",
        "date": "Sat, 18 Jul 2026 17:24:49 GMT",
        "source": "ایرنا",
        "category": "علمی و فناوری",
        "flag": "🇮🇷"
      },
      {
        "title": "حضور۳۹۲ تیم در سیزدهمین دوره مسابقات بین المللی رباتیک و هوش مصنوعی",
        "link": "https://www.irna.ir/news/86212696/%D8%AD%D8%B6%D9%88%D8%B1%DB%B3%DB%B9%DB%B2-%D8%AA%DB%8C%D9%85-%D8%AF%D8%B1-%D8%B3%DB%8C%D8%B2%D8%AF%D9%87%D9%85%DB%8C%D9%86-%D8%AF%D9%88%D8%B1%D9%87-%D9%85%D8%B3%D8%A7%D8%A8%D9%82%D8%A7%D8%AA-%D8%A8%DB%8C%D9%86-%D8%A7%D9%84%D9%85%D9%84%D9%84%DB%8C-%D8%B1%D8%A8%D8%A7%D8%AA%DB%8C%DA%A9-%D9%88-%D9%87%D9%88%D8%B4",
        "date": "Sat, 18 Jul 2026 17:24:16 GMT",
        "source": "ایرنا",
        "category": "علمی و فناوری",
        "flag": "🇮🇷"
      },
      {
        "title": "۶۰ ثانیه با خراسان‌شمالی؛ از تجهیز نانوایی‌ها به سوخت دوم تا زنگ خطر هاری",
        "link": "https://www.irna.ir/news/86212700/%DB%B6%DB%B0-%D8%AB%D8%A7%D9%86%DB%8C%D9%87-%D8%A8%D8%A7-%D8%AE%D8%B1%D8%A7%D8%B3%D8%A7%D9%86-%D8%B4%D9%85%D8%A7%D9%84%DB%8C-%D8%A7%D8%B2-%D8%AA%D8%AC%D9%87%DB%8C%D8%B2-%D9%86%D8%A7%D9%86%D9%88%D8%A7%DB%8C%DB%8C-%D9%87%D8%A7-%D8%A8%D9%87-%D8%B3%D9%88%D8%AE%D8%AA-%D8%AF%D9%88%D9%85-%D8%AA%D8%A7",
        "date": "Sat, 18 Jul 2026 17:04:01 GMT",
        "source": "ایرنا",
        "category": "علمی و فناوری",
        "flag": "🇮🇷"
      }
    ],
    "ورزشی": [
      {
        "title": "قهرمانی دیویس کاپ ایران در گروه ۲ آسیا و اقیانوسیه",
        "link": "https://www.isna.ir/news/1405042716164/%D9%82%D9%87%D8%B1%D9%85%D8%A7%D9%86%DB%8C-%D8%AF%DB%8C%D9%88%DB%8C%D8%B3-%DA%A9%D8%A7%D9%BE-%D8%A7%DB%8C%D8%B1%D8%A7%D9%86-%D8%AF%D8%B1-%DA%AF%D8%B1%D9%88%D9%87-%DB%B2-%D8%A2%D8%B3%DB%8C%D8%A7-%D9%88-%D8%A7%D9%82%DB%8C%D8%A7%D9%86%D9%88%D8%B3%DB%8C%D9%87",
        "date": "Sat, 18 Jul 2026 17:17:46 GMT",
        "source": "ایسنا",
        "category": "ورزشی",
        "flag": "🇮🇷"
      },
      {
        "title": "اسلامی پس از تمدید قرارداد در تمرین استقلال حاضر شد",
        "link": "https://www.irna.ir/news/86212702/%D8%A7%D8%B3%D9%84%D8%A7%D9%85%DB%8C-%D9%BE%D8%B3-%D8%A7%D8%B2-%D8%AA%D9%85%D8%AF%DB%8C%D8%AF-%D9%82%D8%B1%D8%A7%D8%B1%D8%AF%D8%A7%D8%AF-%D8%AF%D8%B1-%D8%AA%D9%85%D8%B1%DB%8C%D9%86-%D8%A7%D8%B3%D8%AA%D9%82%D9%84%D8%A7%D9%84-%D8%AD%D8%A7%D8%B6%D8%B1-%D8%B4%D8%AF",
        "date": "Sat, 18 Jul 2026 17:15:07 GMT",
        "source": "ایرنا",
        "category": "ورزشی",
        "flag": "🇮🇷"
      },
      {
        "title": "ترکیب تیم ملی شطرنج ایران مشخص شد",
        "link": "https://www.isna.ir/news/1405042716160/%D8%AA%D8%B1%DA%A9%DB%8C%D8%A8-%D8%AA%DB%8C%D9%85-%D9%85%D9%84%DB%8C-%D8%B4%D8%B7%D8%B1%D9%86%D8%AC-%D8%A7%DB%8C%D8%B1%D8%A7%D9%86-%D9%85%D8%B4%D8%AE%D8%B5-%D8%B4%D8%AF",
        "date": "Sat, 18 Jul 2026 17:10:59 GMT",
        "source": "ایسنا",
        "category": "ورزشی",
        "flag": "🇮🇷"
      },
      {
        "title": "تیم ملی والیبال نوجوانان ایران بدون شکست بر بام آسیا",
        "link": "https://www.imna.ir/news/989488/%D8%AA%DB%8C%D9%85-%D9%85%D9%84%DB%8C-%D9%88%D8%A7%D9%84%DB%8C%D8%A8%D8%A7%D9%84-%D9%86%D9%88%D8%AC%D9%88%D8%A7%D9%86%D8%A7%D9%86-%D8%A7%DB%8C%D8%B1%D8%A7%D9%86-%D8%A8%D8%AF%D9%88%D9%86-%D8%B4%DA%A9%D8%B3%D8%AA-%D8%A8%D8%B1-%D8%A8%D8%A7%D9%85-%D8%A2%D8%B3%DB%8C%D8%A7",
        "date": "Sat, 18 Jul 2026 17:01:33 GMT",
        "source": "ایمنا",
        "category": "ورزشی",
        "flag": "🇮🇷"
      },
      {
        "title": "نمایشنامه‌هایی از سیدمهدی شجاعی و سیدحسین فدایی‌حسین در سنگلج",
        "link": "https://www.khabaronline.ir/news/2247962/%D9%86%D9%85%D8%A7%DB%8C%D8%B4%D9%86%D8%A7%D9%85%D9%87-%D9%87%D8%A7%DB%8C%DB%8C-%D8%A7%D8%B2-%D8%B3%DB%8C%D8%AF%D9%85%D9%87%D8%AF%DB%8C-%D8%B4%D8%AC%D8%A7%D8%B9%DB%8C-%D9%88-%D8%B3%DB%8C%D8%AF%D8%AD%D8%B3%DB%8C%D9%86-%D9%81%D8%AF%D8%A7%DB%8C%DB%8C-%D8%AD%D8%B3%DB%8C%D9%86-%D8%AF%D8%B1-%D8%B3%D9%86%DA%AF%D9%84%D8%AC",
        "date": "Sat, 18 Jul 2026 17:00:00 GMT",
        "source": "خبرآنلاین",
        "category": "ورزشی",
        "flag": "🇮🇷"
      },
      {
        "title": "وقوع حادثه دریایی برای یک کشتی تجاری نزدیک عمان",
        "link": "https://www.mehrnews.com/news/6891854/%D9%88%D9%82%D9%88%D8%B9-%D8%AD%D8%A7%D8%AF%D8%AB%D9%87-%D8%AF%D8%B1%DB%8C%D8%A7%DB%8C%DB%8C-%D8%A8%D8%B1%D8%A7%DB%8C-%DB%8C%DA%A9-%D9%86%D9%81%D8%AA%DA%A9%D8%B4-%D9%86%D8%B2%D8%AF%DB%8C%DA%A9-%D8%B9%D9%85%D8%A7%D9%86",
        "date": "Sat, 18 Jul 2026 16:57:45 GMT",
        "source": "مهر",
        "category": "ورزشی",
        "flag": "🇮🇷"
      }
    ]
  }
}